Workbook

Sheet Dashboard
B1: U.S. Housing Market Dashboard
B2: Home prices: FHFA HPI (purchase-only, latest quarter 2026 Q2). Loans: CFPB HMDA originations (2018-2025). HPI is an index (1991 Q1 = 100), not a price.
B4: Select a state > | C4: Virginia | F4: Cards, charts, and the highlighted heat-map row update when you change the state. | N4: How to use
N5: 1. Pick a state in the yellow box. 2. The cards and the three charts show that state.
B6: Home price change, YoY (2026 Q2) | D6: Home price change since 2019 Q4 | G6: Loans originated (2025) | J6: Average loan size (2025) | N6: 3. The heat map shows all states. The selected state has a bold row. Latest HPI quarter: 2026 Q2.
B7: =INDEX(Calc!$D$2:$D$52,MATCH($C$4,Calc!$B$2:$B$52,0)) -> 0.030320098 | D7: =INDEX(Calc!$E$2:$E$52,MATCH($C$4,Calc!$B$2:$B$52,0)) -> 0.61808838 | G7: =SUMIFS(tblData[Total loans],tblData[State],$C$4,tblData[Year],2025) -> 164098 | J7: =SUMIFS(tblData[Total dollar volume],tblData[State],$C$4,tblData[Year],2025)/SUMIFS(tblData[Total loans],tblData[State],$C$4,tblData[Year],2025) -> 437686.75
B9: ="U.S.: "&TEXT(Calc!$I$2,"+0.0%;-0.0%;0.0%") -> U.S.: +2.1% | D9: ="U.S.: "&TEXT(Calc!$I$3,"+0.0%;-0.0%;0.0%") -> U.S.: +60.5% | G9: ="vs. 2024: "&TEXT(SUMIFS(tblData[Total loans],tblData[State],$C$4,tblData[Year],2025)/SUMIFS(tblData[Total loans],tblData[State],$C$4,tblData[Year],2024)-1,"+0.0%;-0.0%;0.0%") -> vs. 2024: +12.7% | J9: ="U.S.: "&TEXT(Calc!$I$4,"$#,##0") -> U.S.: $397,321
B11: Heat map: Q4 home price change, year over year (FHFA HPI, purchase-only, index_nsa)
B12: State | C12: 2018 | D12: 2019 | E12: 2020 | F12: 2021 | G12: 2022 | H12: 2023 | I12: 2024 | J12: 2025 | K12: Price trend | L12: Loans trend
B13: Alabama | C13: =SUMIFS(tblData[Q4 HPI YoY change],tblData[State],$B13,tblData[Year],C$12) -> 0.046723 | D13: =SUMIFS(tblData[Q4 HPI YoY change],tblData[State],$B13,tblData[Year],D$12) -> 0.065616 | E13: =SUMIFS(tblData[Q4 HPI YoY change],tblData[State],$B13,tblData[Year],E$12) -> 0.113352 | F13: =SUMIFS(tblData[Q4 HPI YoY change],tblData[State],$B13,tblData[Year],F$12) -> 0.170088 | G13: =SUMIFS(tblData[Q4 HPI YoY change],tblData[State],$B13,tblData[Year],G$12) -> 0.09743 | H13: =SUMIFS(tblData[Q4 HPI YoY change],tblData[State],$B13,tblData[Year],H$12) -> 0.041433 | I13: =SUMIFS(tblData[Q4 HPI YoY change],tblData[State],$B13,tblData[Year],I$12) -> 0.048609 | J13: =SUMIFS(tblData[Q4 HPI YoY change],tblData[State],$B13,tblData[Year],J$12) -> 0.024969
B14: Alaska | C14: =SUMIFS(tblData[Q4 HPI YoY change],tblData[State],$B14,tblData[Year],C$12) -> 0.013034 | D14: =SUMIFS(tblData[Q4 HPI YoY change],tblData[State],$B14,tblData[Year],D$12) -> 0.040887 | E14: =SUMIFS(tblData[Q4 HPI YoY change],tblData[State],$B14,tblData[Year],E$12) -> 0.085273 | F14: =SUMIFS(tblData[Q4 HPI YoY change],tblData[State],$B14,tblData[Year],F$12) -> 0.104741 | G14: =SUMIFS(tblData[Q4 HPI YoY change],tblData[State],$B14,tblData[Year],G$12) -> 0.055185 | H14: =SUMIFS(tblData[Q4 HPI YoY change],tblData[State],$B14,tblData[Year],H$12) -> 0.064347 | I14: =SUMIFS(tblData[Q4 HPI YoY change],tblData[State],$B14,tblData[Year],I$12) -> 0.038606 | J14: =SUMIFS(tblData[Q4 HPI YoY change],tblData[State],$B14,tblData[Year],J$12) -> 0.045982
B15: Arizona | C15: =SUMIFS(tblData[Q4 HPI YoY change],tblData[State],$B15,tblData[Year],C$12) -> 0.083673 | D15: =SUMIFS(tblData[Q4 HPI YoY change],tblData[State],$B15,tblData[Year],D$12) -> 0.079201 | E15: =SUMIFS(tblData[Q4 HPI YoY change],tblData[State],$B15,tblData[Year],E$12) -> 0.141687 | F15: =SUMIFS(tblData[Q4 HPI YoY change],tblData[State],$B15,tblData[Year],F$12) -> 0.272187 | G15: =SUMIFS(tblData[Q4 HPI YoY change],tblData[State],$B15,tblData[Year],G$12) -> 0.051615 | H15: =SUMIFS(tblData[Q4 HPI YoY change],tblData[State],$B15,tblData[Year],H$12) -> 0.057833 | I15: =SUMIFS(tblData[Q4 HPI YoY change],tblData[State],$B15,tblData[Year],I$12) -> 0.018212 | J15: =SUMIFS(tblData[Q4 HPI YoY change],tblData[State],$B15,tblData[Year],J$12) -> 0.00777
B16: Arkansas | C16: =SUMIFS(tblData[Q4 HPI YoY change],tblData[State],$B16,tblData[Year],C$12) -> 0.033379 | D16: =SUMIFS(tblData[Q4 HPI YoY change],tblData[State],$B16,tblData[Year],D$12) -> 0.039187 | E16: =SUMIFS(tblData[Q4 HPI YoY change],tblData[State],$B16,tblData[Year],E$12) -> 0.108858 | F16: =SUMIFS(tblData[Q4 HPI YoY change],tblData[State],$B16,tblData[Year],F$12) -> 0.185314 | G16: =SUMIFS(tblData[Q4 HPI YoY change],tblData[State],$B16,tblData[Year],G$12) -> 0.093785 | H16: =SUMIFS(tblData[Q4 HPI YoY change],tblData[State],$B16,tblData[Year],H$12) -> 0.056389 | I16: =SUMIFS(tblData[Q4 HPI YoY change],tblData[State],$B16,tblData[Year],I$12) -> 0.043951 | J16: =SUMIFS(tblData[Q4 HPI YoY change],tblData[State],$B16,tblData[Year],J$12) -> 0.040333
B17: California | C17: =SUMIFS(tblData[Q4 HPI YoY change],tblData[State],$B17,tblData[Year],C$12) -> 0.048003 | D17: =SUMIFS(tblData[Q4 HPI YoY change],tblData[State],$B17,tblData[Year],D$12) -> 0.044401 | E17: =SUMIFS(tblData[Q4 HPI YoY change],tblData[State],$B17,tblData[Year],E$12) -> 0.115793 | F17: =SUMIFS(tblData[Q4 HPI YoY change],tblData[State],$B17,tblData[Year],F$12) -> 0.191342 | G17: =SUMIFS(tblData[Q4 HPI YoY change],tblData[State],$B17,tblData[Year],G$12) -> 0.012414 | H17: =SUMIFS(tblData[Q4 HPI YoY change],tblData[State],$B17,tblData[Year],H$12) -> 0.048409 | I17: =SUMIFS(tblData[Q4 HPI YoY change],tblData[State],$B17,tblData[Year],I$12) -> 0.024759 | J17: =SUMIFS(tblData[Q4 HPI YoY change],tblData[State],$B17,tblData[Year],J$12) -> -0.00467
B18: Colorado | C18: =SUMIFS(tblData[Q4 HPI YoY change],tblData[State],$B18,tblData[Year],C$12) -> 0.068277 | D18: =SUMIFS(tblData[Q4 HPI YoY change],tblData[State],$B18,tblData[Year],D$12) -> 0.061513 | E18: =SUMIFS(tblData[Q4 HPI YoY change],tblData[State],$B18,tblData[Year],E$12) -> 0.108056 | F18: =SUMIFS(tblData[Q4 HPI YoY change],tblData[State],$B18,tblData[Year],F$12) -> 0.180695 | G18: =SUMIFS(tblData[Q4 HPI YoY change],tblData[State],$B18,tblData[Year],G$12) -> 0.047234 | H18: =SUMIFS(tblData[Q4 HPI YoY change],tblData[State],$B18,tblData[Year],H$12) -> 0.030588 | I18: =SUMIFS(tblData[Q4 HPI YoY change],tblData[State],$B18,tblData[Year],I$12) -> 0.022227 | J18: =SUMIFS(tblData[Q4 HPI YoY change],tblData[State],$B18,tblData[Year],J$12) -> -0.014876
B19: Connecticut | C19: =SUMIFS(tblData[Q4 HPI YoY change],tblData[State],$B19,tblData[Year],C$12) -> 0.023047 | D19: =SUMIFS(tblData[Q4 HPI YoY change],tblData[State],$B19,tblData[Year],D$12) -> 0.023353 | E19: =SUMIFS(tblData[Q4 HPI YoY change],tblData[State],$B19,tblData[Year],E$12) -> 0.135135 | F19: =SUMIFS(tblData[Q4 HPI YoY change],tblData[State],$B19,tblData[Year],F$12) -> 0.137121 | G19: =SUMIFS(tblData[Q4 HPI YoY change],tblData[State],$B19,tblData[Year],G$12) -> 0.088174 | H19: =SUMIFS(tblData[Q4 HPI YoY change],tblData[State],$B19,tblData[Year],H$12) -> 0.114507 | I19: =SUMIFS(tblData[Q4 HPI YoY change],tblData[State],$B19,tblData[Year],I$12) -> 0.089085 | J19: =SUMIFS(tblData[Q4 HPI YoY change],tblData[State],$B19,tblData[Year],J$12) -> 0.046341
B20: Delaware | C20: =SUMIFS(tblData[Q4 HPI YoY change],tblData[State],$B20,tblData[Year],C$12) -> 0.039282 | D20: =SUMIFS(tblData[Q4 HPI YoY change],tblData[State],$B20,tblData[Year],D$12) -> 0.070614 | E20: =SUMIFS(tblData[Q4 HPI YoY change],tblData[State],$B20,tblData[Year],E$12) -> 0.083585 | F20: =SUMIFS(tblData[Q4 HPI YoY change],tblData[State],$B20,tblData[Year],F$12) -> 0.153717 | G20: =SUMIFS(tblData[Q4 HPI YoY change],tblData[State],$B20,tblData[Year],G$12) -> 0.121628 | H20: =SUMIFS(tblData[Q4 HPI YoY change],tblData[State],$B20,tblData[Year],H$12) -> 0.045877 | I20: =SUMIFS(tblData[Q4 HPI YoY change],tblData[State],$B20,tblData[Year],I$12) -> 0.035142 | J20: =SUMIFS(tblData[Q4 HPI YoY change],tblData[State],$B20,tblData[Year],J$12) -> 0.069829
B21: District of Columbia | C21: =SUMIFS(tblData[Q4 HPI YoY change],tblData[State],$B21,tblData[Year],C$12) -> 0.058342 | D21: =SUMIFS(tblData[Q4 HPI YoY change],tblData[State],$B21,tblData[Year],D$12) -> 0.049369 | E21: =SUMIFS(tblData[Q4 HPI YoY change],tblData[State],$B21,tblData[Year],E$12) -> 0.034729 | F21: =SUMIFS(tblData[Q4 HPI YoY change],tblData[State],$B21,tblData[Year],F$12) -> 0.062777 | G21: =SUMIFS(tblData[Q4 HPI YoY change],tblData[State],$B21,tblData[Year],G$12) -> -0.041901 | H21: =SUMIFS(tblData[Q4 HPI YoY change],tblData[State],$B21,tblData[Year],H$12) -> 0.019263 | I21: =SUMIFS(tblData[Q4 HPI YoY change],tblData[State],$B21,tblData[Year],I$12) -> 0.02895 | J21: =SUMIFS(tblData[Q4 HPI YoY change],tblData[State],$B21,tblData[Year],J$12) -> -0.010255
B22: Florida | C22: =SUMIFS(tblData[Q4 HPI YoY change],tblData[State],$B22,tblData[Year],C$12) -> 0.069383 | D22: =SUMIFS(tblData[Q4 HPI YoY change],tblData[State],$B22,tblData[Year],D$12) -> 0.061315 | E22: =SUMIFS(tblData[Q4 HPI YoY change],tblData[State],$B22,tblData[Year],E$12) -> 0.118657 | F22: =SUMIFS(tblData[Q4 HPI YoY change],tblData[State],$B22,tblData[Year],F$12) -> 0.255416 | G22: =SUMIFS(tblData[Q4 HPI YoY change],tblData[State],$B22,tblData[Year],G$12) -> 0.130702 | H22: =SUMIFS(tblData[Q4 HPI YoY change],tblData[State],$B22,tblData[Year],H$12) -> 0.062616 | I22: =SUMIFS(tblData[Q4 HPI YoY change],tblData[State],$B22,tblData[Year],I$12) -> 0.020871 | J22: =SUMIFS(tblData[Q4 HPI YoY change],tblData[State],$B22,tblData[Year],J$12) -> -0.022847
B23: Georgia | C23: =SUMIFS(tblData[Q4 HPI YoY change],tblData[State],$B23,tblData[Year],C$12) -> 0.07463 | D23: =SUMIFS(tblData[Q4 HPI YoY change],tblData[State],$B23,tblData[Year],D$12) -> 0.066356 | E23: =SUMIFS(tblData[Q4 HPI YoY change],tblData[State],$B23,tblData[Year],E$12) -> 0.116115 | F23: =SUMIFS(tblData[Q4 HPI YoY change],tblData[State],$B23,tblData[Year],F$12) -> 0.205864 | G23: =SUMIFS(tblData[Q4 HPI YoY change],tblData[State],$B23,tblData[Year],G$12) -> 0.111059 | H23: =SUMIFS(tblData[Q4 HPI YoY change],tblData[State],$B23,tblData[Year],H$12) -> 0.064505 | I23: =SUMIFS(tblData[Q4 HPI YoY change],tblData[State],$B23,tblData[Year],I$12) -> 0.048148 | J23: =SUMIFS(tblData[Q4 HPI YoY change],tblData[State],$B23,tblData[Year],J$12) -> -0.000119
B24: Hawaii | C24: =SUMIFS(tblData[Q4 HPI YoY change],tblData[State],$B24,tblData[Year],C$12) -> 0.025632 | D24: =SUMIFS(tblData[Q4 HPI YoY change],tblData[State],$B24,tblData[Year],D$12) -> 0.037944 | E24: =SUMIFS(tblData[Q4 HPI YoY change],tblData[State],$B24,tblData[Year],E$12) -> 0.064385 | F24: =SUMIFS(tblData[Q4 HPI YoY change],tblData[State],$B24,tblData[Year],F$12) -> 0.206107 | G24: =SUMIFS(tblData[Q4 HPI YoY change],tblData[State],$B24,tblData[Year],G$12) -> 0.156991 | H24: =SUMIFS(tblData[Q4 HPI YoY change],tblData[State],$B24,tblData[Year],H$12) -> -0.035076 | I24: =SUMIFS(tblData[Q4 HPI YoY change],tblData[State],$B24,tblData[Year],I$12) -> 0.030448 | J24: =SUMIFS(tblData[Q4 HPI YoY change],tblData[State],$B24,tblData[Year],J$12) -> 0.004199
B25: Idaho | C25: =SUMIFS(tblData[Q4 HPI YoY change],tblData[State],$B25,tblData[Year],C$12) -> 0.123137 | D25: =SUMIFS(tblData[Q4 HPI YoY change],tblData[State],$B25,tblData[Year],D$12) -> 0.130599 | E25: =SUMIFS(tblData[Q4 HPI YoY change],tblData[State],$B25,tblData[Year],E$12) -> 0.202348 | F25: =SUMIFS(tblData[Q4 HPI YoY change],tblData[State],$B25,tblData[Year],F$12) -> 0.275594 | G25: =SUMIFS(tblData[Q4 HPI YoY change],tblData[State],$B25,tblData[Year],G$12) -> 0.02263 | H25: =SUMIFS(tblData[Q4 HPI YoY change],tblData[State],$B25,tblData[Year],H$12) -> 0.020462 | I25: =SUMIFS(tblData[Q4 HPI YoY change],tblData[State],$B25,tblData[Year],I$12) -> 0.055138 | J25: =SUMIFS(tblData[Q4 HPI YoY change],tblData[State],$B25,tblData[Year],J$12) -> -0.008246
B26: Illinois | C26: =SUMIFS(tblData[Q4 HPI YoY change],tblData[State],$B26,tblData[Year],C$12) -> 0.023629 | D26: =SUMIFS(tblData[Q4 HPI YoY change],tblData[State],$B26,tblData[Year],D$12) -> 0.030881 | E26: =SUMIFS(tblData[Q4 HPI YoY change],tblData[State],$B26,tblData[Year],E$12) -> 0.08171 | F26: =SUMIFS(tblData[Q4 HPI YoY change],tblData[State],$B26,tblData[Year],F$12) -> 0.119865 | G26: =SUMIFS(tblData[Q4 HPI YoY change],tblData[State],$B26,tblData[Year],G$12) -> 0.068677 | H26: =SUMIFS(tblData[Q4 HPI YoY change],tblData[State],$B26,tblData[Year],H$12) -> 0.084654 | I26: =SUMIFS(tblData[Q4 HPI YoY change],tblData[State],$B26,tblData[Year],I$12) -> 0.074245 | J26: =SUMIFS(tblData[Q4 HPI YoY change],tblData[State],$B26,tblData[Year],J$12) -> 0.063674 | N26: Source: CFPB HMDA, originated loans, 2018-2025 (latest HMDA year: 2025).
B27: Indiana | C27: =SUMIFS(tblData[Q4 HPI YoY change],tblData[State],$B27,tblData[Year],C$12) -> 0.063266 | D27: =SUMIFS(tblData[Q4 HPI YoY change],tblData[State],$B27,tblData[Year],D$12) -> 0.070688 | E27: =SUMIFS(tblData[Q4 HPI YoY change],tblData[State],$B27,tblData[Year],E$12) -> 0.122945 | F27: =SUMIFS(tblData[Q4 HPI YoY change],tblData[State],$B27,tblData[Year],F$12) -> 0.145498 | G27: =SUMIFS(tblData[Q4 HPI YoY change],tblData[State],$B27,tblData[Year],G$12) -> 0.088506 | H27: =SUMIFS(tblData[Q4 HPI YoY change],tblData[State],$B27,tblData[Year],H$12) -> 0.072336 | I27: =SUMIFS(tblData[Q4 HPI YoY change],tblData[State],$B27,tblData[Year],I$12) -> 0.065087 | J27: =SUMIFS(tblData[Q4 HPI YoY change],tblData[State],$B27,tblData[Year],J$12) -> 0.033455
B28: Iowa | C28: =SUMIFS(tblData[Q4 HPI YoY change],tblData[State],$B28,tblData[Year],C$12) -> 0.042857 | D28: =SUMIFS(tblData[Q4 HPI YoY change],tblData[State],$B28,tblData[Year],D$12) -> 0.030371 | E28: =SUMIFS(tblData[Q4 HPI YoY change],tblData[State],$B28,tblData[Year],E$12) -> 0.081794 | F28: =SUMIFS(tblData[Q4 HPI YoY change],tblData[State],$B28,tblData[Year],F$12) -> 0.110128 | G28: =SUMIFS(tblData[Q4 HPI YoY change],tblData[State],$B28,tblData[Year],G$12) -> 0.084251 | H28: =SUMIFS(tblData[Q4 HPI YoY change],tblData[State],$B28,tblData[Year],H$12) -> 0.058423 | I28: =SUMIFS(tblData[Q4 HPI YoY change],tblData[State],$B28,tblData[Year],I$12) -> 0.050961 | J28: =SUMIFS(tblData[Q4 HPI YoY change],tblData[State],$B28,tblData[Year],J$12) -> 0.037492
B29: Kansas | C29: =SUMIFS(tblData[Q4 HPI YoY change],tblData[State],$B29,tblData[Year],C$12) -> 0.054257 | D29: =SUMIFS(tblData[Q4 HPI YoY change],tblData[State],$B29,tblData[Year],D$12) -> 0.053045 | E29: =SUMIFS(tblData[Q4 HPI YoY change],tblData[State],$B29,tblData[Year],E$12) -> 0.109123 | F29: =SUMIFS(tblData[Q4 HPI YoY change],tblData[State],$B29,tblData[Year],F$12) -> 0.127275 | G29: =SUMIFS(tblData[Q4 HPI YoY change],tblData[State],$B29,tblData[Year],G$12) -> 0.081622 | H29: =SUMIFS(tblData[Q4 HPI YoY change],tblData[State],$B29,tblData[Year],H$12) -> 0.077653 | I29: =SUMIFS(tblData[Q4 HPI YoY change],tblData[State],$B29,tblData[Year],I$12) -> 0.055738 | J29: =SUMIFS(tblData[Q4 HPI YoY change],tblData[State],$B29,tblData[Year],J$12) -> 0.040752
B30: Kentucky | C30: =SUMIFS(tblData[Q4 HPI YoY change],tblData[State],$B30,tblData[Year],C$12) -> 0.049815 | D30: =SUMIFS(tblData[Q4 HPI YoY change],tblData[State],$B30,tblData[Year],D$12) -> 0.042367 | E30: =SUMIFS(tblData[Q4 HPI YoY change],tblData[State],$B30,tblData[Year],E$12) -> 0.111897 | F30: =SUMIFS(tblData[Q4 HPI YoY change],tblData[State],$B30,tblData[Year],F$12) -> 0.140152 | G30: =SUMIFS(tblData[Q4 HPI YoY change],tblData[State],$B30,tblData[Year],G$12) -> 0.093972 | H30: =SUMIFS(tblData[Q4 HPI YoY change],tblData[State],$B30,tblData[Year],H$12) -> 0.058498 | I30: =SUMIFS(tblData[Q4 HPI YoY change],tblData[State],$B30,tblData[Year],I$12) -> 0.065426 | J30: =SUMIFS(tblData[Q4 HPI YoY change],tblData[State],$B30,tblData[Year],J$12) -> 0.028846
B31: Louisiana | C31: =SUMIFS(tblData[Q4 HPI YoY change],tblData[State],$B31,tblData[Year],C$12) -> 0.020333 | D31: =SUMIFS(tblData[Q4 HPI YoY change],tblData[State],$B31,tblData[Year],D$12) -> 0.028804 | E31: =SUMIFS(tblData[Q4 HPI YoY change],tblData[State],$B31,tblData[Year],E$12) -> 0.062828 | F31: =SUMIFS(tblData[Q4 HPI YoY change],tblData[State],$B31,tblData[Year],F$12) -> 0.102555 | G31: =SUMIFS(tblData[Q4 HPI YoY change],tblData[State],$B31,tblData[Year],G$12) -> 0.047635 | H31: =SUMIFS(tblData[Q4 HPI YoY change],tblData[State],$B31,tblData[Year],H$12) -> 0.018015 | I31: =SUMIFS(tblData[Q4 HPI YoY change],tblData[State],$B31,tblData[Year],I$12) -> 0.006143 | J31: =SUMIFS(tblData[Q4 HPI YoY change],tblData[State],$B31,tblData[Year],J$12) -> 0.034617
B32: Maine | C32: =SUMIFS(tblData[Q4 HPI YoY change],tblData[State],$B32,tblData[Year],C$12) -> 0.069832 | D32: =SUMIFS(tblData[Q4 HPI YoY change],tblData[State],$B32,tblData[Year],D$12) -> 0.065837 | E32: =SUMIFS(tblData[Q4 HPI YoY change],tblData[State],$B32,tblData[Year],E$12) -> 0.140122 | F32: =SUMIFS(tblData[Q4 HPI YoY change],tblData[State],$B32,tblData[Year],F$12) -> 0.201607 | G32: =SUMIFS(tblData[Q4 HPI YoY change],tblData[State],$B32,tblData[Year],G$12) -> 0.125361 | H32: =SUMIFS(tblData[Q4 HPI YoY change],tblData[State],$B32,tblData[Year],H$12) -> 0.062433 | I32: =SUMIFS(tblData[Q4 HPI YoY change],tblData[State],$B32,tblData[Year],I$12) -> 0.074502 | J32: =SUMIFS(tblData[Q4 HPI YoY change],tblData[State],$B32,tblData[Year],J$12) -> 0.039422
B33: Maryland | C33: =SUMIFS(tblData[Q4 HPI YoY change],tblData[State],$B33,tblData[Year],C$12) -> 0.014273 | D33: =SUMIFS(tblData[Q4 HPI YoY change],tblData[State],$B33,tblData[Year],D$12) -> 0.032246 | E33: =SUMIFS(tblData[Q4 HPI YoY change],tblData[State],$B33,tblData[Year],E$12) -> 0.102182 | F33: =SUMIFS(tblData[Q4 HPI YoY change],tblData[State],$B33,tblData[Year],F$12) -> 0.107998 | G33: =SUMIFS(tblData[Q4 HPI YoY change],tblData[State],$B33,tblData[Year],G$12) -> 0.060533 | H33: =SUMIFS(tblData[Q4 HPI YoY change],tblData[State],$B33,tblData[Year],H$12) -> 0.053917 | I33: =SUMIFS(tblData[Q4 HPI YoY change],tblData[State],$B33,tblData[Year],I$12) -> 0.058991 | J33: =SUMIFS(tblData[Q4 HPI YoY change],tblData[State],$B33,tblData[Year],J$12) -> 0.012015
B34: Massachusetts | C34: =SUMIFS(tblData[Q4 HPI YoY change],tblData[State],$B34,tblData[Year],C$12) -> 0.051898 | D34: =SUMIFS(tblData[Q4 HPI YoY change],tblData[State],$B34,tblData[Year],D$12) -> 0.053945 | E34: =SUMIFS(tblData[Q4 HPI YoY change],tblData[State],$B34,tblData[Year],E$12) -> 0.111851 | F34: =SUMIFS(tblData[Q4 HPI YoY change],tblData[State],$B34,tblData[Year],F$12) -> 0.145 | G34: =SUMIFS(tblData[Q4 HPI YoY change],tblData[State],$B34,tblData[Year],G$12) -> 0.050164 | H34: =SUMIFS(tblData[Q4 HPI YoY change],tblData[State],$B34,tblData[Year],H$12) -> 0.087184 | I34: =SUMIFS(tblData[Q4 HPI YoY change],tblData[State],$B34,tblData[Year],I$12) -> 0.055343 | J34: =SUMIFS(tblData[Q4 HPI YoY change],tblData[State],$B34,tblData[Year],J$12) -> 0.02473
B35: Michigan | C35: =SUMIFS(tblData[Q4 HPI YoY change],tblData[State],$B35,tblData[Year],C$12) -> 0.068625 | D35: =SUMIFS(tblData[Q4 HPI YoY change],tblData[State],$B35,tblData[Year],D$12) -> 0.056864 | E35: =SUMIFS(tblData[Q4 HPI YoY change],tblData[State],$B35,tblData[Year],E$12) -> 0.111342 | F35: =SUMIFS(tblData[Q4 HPI YoY change],tblData[State],$B35,tblData[Year],F$12) -> 0.148944 | G35: =SUMIFS(tblData[Q4 HPI YoY change],tblData[State],$B35,tblData[Year],G$12) -> 0.062741 | H35: =SUMIFS(tblData[Q4 HPI YoY change],tblData[State],$B35,tblData[Year],H$12) -> 0.088399 | I35: =SUMIFS(tblData[Q4 HPI YoY change],tblData[State],$B35,tblData[Year],I$12) -> 0.050737 | J35: =SUMIFS(tblData[Q4 HPI YoY change],tblData[State],$B35,tblData[Year],J$12) -> 0.05854
B36: Minnesota | C36: =SUMIFS(tblData[Q4 HPI YoY change],tblData[State],$B36,tblData[Year],C$12) -> 0.054614 | D36: =SUMIFS(tblData[Q4 HPI YoY change],tblData[State],$B36,tblData[Year],D$12) -> 0.056821 | E36: =SUMIFS(tblData[Q4 HPI YoY change],tblData[State],$B36,tblData[Year],E$12) -> 0.09584 | F36: =SUMIFS(tblData[Q4 HPI YoY change],tblData[State],$B36,tblData[Year],F$12) -> 0.122799 | G36: =SUMIFS(tblData[Q4 HPI YoY change],tblData[State],$B36,tblData[Year],G$12) -> 0.044687 | H36: =SUMIFS(tblData[Q4 HPI YoY change],tblData[State],$B36,tblData[Year],H$12) -> 0.042144 | I36: =SUMIFS(tblData[Q4 HPI YoY change],tblData[State],$B36,tblData[Year],I$12) -> 0.04599 | J36: =SUMIFS(tblData[Q4 HPI YoY change],tblData[State],$B36,tblData[Year],J$12) -> 0.032849
B37: Mississippi | C37: =SUMIFS(tblData[Q4 HPI YoY change],tblData[State],$B37,tblData[Year],C$12) -> 0.05883 | D37: =SUMIFS(tblData[Q4 HPI YoY change],tblData[State],$B37,tblData[Year],D$12) -> 0.031616 | E37: =SUMIFS(tblData[Q4 HPI YoY change],tblData[State],$B37,tblData[Year],E$12) -> 0.07939 | F37: =SUMIFS(tblData[Q4 HPI YoY change],tblData[State],$B37,tblData[Year],F$12) -> 0.154781 | G37: =SUMIFS(tblData[Q4 HPI YoY change],tblData[State],$B37,tblData[Year],G$12) -> 0.074105 | H37: =SUMIFS(tblData[Q4 HPI YoY change],tblData[State],$B37,tblData[Year],H$12) -> 0.10409 | I37: =SUMIFS(tblData[Q4 HPI YoY change],tblData[State],$B37,tblData[Year],I$12) -> -0.006794 | J37: =SUMIFS(tblData[Q4 HPI YoY change],tblData[State],$B37,tblData[Year],J$12) -> 0.030845
B38: Missouri | C38: =SUMIFS(tblData[Q4 HPI YoY change],tblData[State],$B38,tblData[Year],C$12) -> 0.06051 | D38: =SUMIFS(tblData[Q4 HPI YoY change],tblData[State],$B38,tblData[Year],D$12) -> 0.060645 | E38: =SUMIFS(tblData[Q4 HPI YoY change],tblData[State],$B38,tblData[Year],E$12) -> 0.104047 | F38: =SUMIFS(tblData[Q4 HPI YoY change],tblData[State],$B38,tblData[Year],F$12) -> 0.151975 | G38: =SUMIFS(tblData[Q4 HPI YoY change],tblData[State],$B38,tblData[Year],G$12) -> 0.082252 | H38: =SUMIFS(tblData[Q4 HPI YoY change],tblData[State],$B38,tblData[Year],H$12) -> 0.070647 | I38: =SUMIFS(tblData[Q4 HPI YoY change],tblData[State],$B38,tblData[Year],I$12) -> 0.053062 | J38: =SUMIFS(tblData[Q4 HPI YoY change],tblData[State],$B38,tblData[Year],J$12) -> 0.046366
... B41: Nevada | C41: =SUMIFS(tblData[Q4 HPI YoY change],tblData[State],$B41,tblData[Year],C$12) -> 0.100194 | D41: =SUMIFS(tblData[Q4 HPI YoY change],tblData[State],$B41,tblData[Year],D$12) -> 0.044329 | E41: =SUMIFS(tblData[Q4 HPI YoY change],tblData[State],$B41,tblData[Year],E$12) -> 0.106814 | F41: =SUMIFS(tblData[Q4 HPI YoY change],tblData[State],$B41,tblData[Year],F$12) -> 0.231992 | G41: =SUMIFS(tblData[Q4 HPI YoY change],tblData[State],$B41,tblData[Year],G$12) -> 0.029086 | H41: =SUMIFS(tblData[Q4 HPI YoY change],tblData[State],$B41,tblData[Year],H$12) -> 0.035683 | I41: =SUMIFS(tblData[Q4 HPI YoY change],tblData[State],$B41,tblData[Year],I$12) -> 0.061365 | J41: =SUMIFS(tblData[Q4 HPI YoY change],tblData[State],$B41,tblData[Year],J$12) -> 0.007058
B42: New Hampshire | C42: =SUMIFS(tblData[Q4 HPI YoY change],tblData[State],$B42,tblData[Year],C$12) -> 0.056091 | D42: =SUMIFS(tblData[Q4 HPI YoY change],tblData[State],$B42,tblData[Year],D$12) -> 0.055404 | E42: =SUMIFS(tblData[Q4 HPI YoY change],tblData[State],$B42,tblData[Year],E$12) -> 0.143124 | F42: =SUMIFS(tblData[Q4 HPI YoY change],tblData[State],$B42,tblData[Year],F$12) -> 0.180258 | G42: =SUMIFS(tblData[Q4 HPI YoY change],tblData[State],$B42,tblData[Year],G$12) -> 0.09315 | H42: =SUMIFS(tblData[Q4 HPI YoY change],tblData[State],$B42,tblData[Year],H$12) -> 0.091799 | I42: =SUMIFS(tblData[Q4 HPI YoY change],tblData[State],$B42,tblData[Year],I$12) -> 0.075209 | J42: =SUMIFS(tblData[Q4 HPI YoY change],tblData[State],$B42,tblData[Year],J$12) -> 0.038506 | N42: Source: FHFA HPI, purchase-only, index_nsa (not seasonally adjusted). U.S. = FHFA quarterly U.S. index. Years 2018-2025.
B43: New Jersey | C43: =SUMIFS(tblData[Q4 HPI YoY change],tblData[State],$B43,tblData[Year],C$12) -> 0.035622 | D43: =SUMIFS(tblData[Q4 HPI YoY change],tblData[State],$B43,tblData[Year],D$12) -> 0.046998 | E43: =SUMIFS(tblData[Q4 HPI YoY change],tblData[State],$B43,tblData[Year],E$12) -> 0.120857 | F43: =SUMIFS(tblData[Q4 HPI YoY change],tblData[State],$B43,tblData[Year],F$12) -> 0.150044 | G43: =SUMIFS(tblData[Q4 HPI YoY change],tblData[State],$B43,tblData[Year],G$12) -> 0.080391 | H43: =SUMIFS(tblData[Q4 HPI YoY change],tblData[State],$B43,tblData[Year],H$12) -> 0.112325 | I43: =SUMIFS(tblData[Q4 HPI YoY change],tblData[State],$B43,tblData[Year],I$12) -> 0.087198 | J43: =SUMIFS(tblData[Q4 HPI YoY change],tblData[State],$B43,tblData[Year],J$12) -> 0.049905
B44: New Mexico | C44: =SUMIFS(tblData[Q4 HPI YoY change],tblData[State],$B44,tblData[Year],C$12) -> 0.040888 | D44: =SUMIFS(tblData[Q4 HPI YoY change],tblData[State],$B44,tblData[Year],D$12) -> 0.054617 | E44: =SUMIFS(tblData[Q4 HPI YoY change],tblData[State],$B44,tblData[Year],E$12) -> 0.115241 | F44: =SUMIFS(tblData[Q4 HPI YoY change],tblData[State],$B44,tblData[Year],F$12) -> 0.149212 | G44: =SUMIFS(tblData[Q4 HPI YoY change],tblData[State],$B44,tblData[Year],G$12) -> 0.096742 | H44: =SUMIFS(tblData[Q4 HPI YoY change],tblData[State],$B44,tblData[Year],H$12) -> 0.051891 | I44: =SUMIFS(tblData[Q4 HPI YoY change],tblData[State],$B44,tblData[Year],I$12) -> 0.059218 | J44: =SUMIFS(tblData[Q4 HPI YoY change],tblData[State],$B44,tblData[Year],J$12) -> 0.005933
B45: New York | C45: =SUMIFS(tblData[Q4 HPI YoY change],tblData[State],$B45,tblData[Year],C$12) -> 0.045687 | D45: =SUMIFS(tblData[Q4 HPI YoY change],tblData[State],$B45,tblData[Year],D$12) -> 0.048531 | E45: =SUMIFS(tblData[Q4 HPI YoY change],tblData[State],$B45,tblData[Year],E$12) -> 0.107852 | F45: =SUMIFS(tblData[Q4 HPI YoY change],tblData[State],$B45,tblData[Year],F$12) -> 0.133384 | G45: =SUMIFS(tblData[Q4 HPI YoY change],tblData[State],$B45,tblData[Year],G$12) -> 0.075436 | H45: =SUMIFS(tblData[Q4 HPI YoY change],tblData[State],$B45,tblData[Year],H$12) -> 0.092514 | I45: =SUMIFS(tblData[Q4 HPI YoY change],tblData[State],$B45,tblData[Year],I$12) -> 0.074105 | J45: =SUMIFS(tblData[Q4 HPI YoY change],tblData[State],$B45,tblData[Year],J$12) -> 0.055681
B46: North Carolina | C46: =SUMIFS(tblData[Q4 HPI YoY change],tblData[State],$B46,tblData[Year],C$12) -> 0.063604 | D46: =SUMIFS(tblData[Q4 HPI YoY change],tblData[State],$B46,tblData[Year],D$12) -> 0.066754 | E46: =SUMIFS(tblData[Q4 HPI YoY change],tblData[State],$B46,tblData[Year],E$12) -> 0.119899 | F46: =SUMIFS(tblData[Q4 HPI YoY change],tblData[State],$B46,tblData[Year],F$12) -> 0.210103 | G46: =SUMIFS(tblData[Q4 HPI YoY change],tblData[State],$B46,tblData[Year],G$12) -> 0.127769 | H46: =SUMIFS(tblData[Q4 HPI YoY change],tblData[State],$B46,tblData[Year],H$12) -> 0.059891 | I46: =SUMIFS(tblData[Q4 HPI YoY change],tblData[State],$B46,tblData[Year],I$12) -> 0.053946 | J46: =SUMIFS(tblData[Q4 HPI YoY change],tblData[State],$B46,tblData[Year],J$12) -> 0.010829
B47: North Dakota | C47: =SUMIFS(tblData[Q4 HPI YoY change],tblData[State],$B47,tblData[Year],C$12) -> 0.023532 | D47: =SUMIFS(tblData[Q4 HPI YoY change],tblData[State],$B47,tblData[Year],D$12) -> 0.020141 | E47: =SUMIFS(tblData[Q4 HPI YoY change],tblData[State],$B47,tblData[Year],E$12) -> 0.069102 | F47: =SUMIFS(tblData[Q4 HPI YoY change],tblData[State],$B47,tblData[Year],F$12) -> 0.102224 | G47: =SUMIFS(tblData[Q4 HPI YoY change],tblData[State],$B47,tblData[Year],G$12) -> 0.060258 | H47: =SUMIFS(tblData[Q4 HPI YoY change],tblData[State],$B47,tblData[Year],H$12) -> 0.05259 | I47: =SUMIFS(tblData[Q4 HPI YoY change],tblData[State],$B47,tblData[Year],I$12) -> 0.029519 | J47: =SUMIFS(tblData[Q4 HPI YoY change],tblData[State],$B47,tblData[Year],J$12) -> 0.062597
B48: Ohio | C48: =SUMIFS(tblData[Q4 HPI YoY change],tblData[State],$B48,tblData[Year],C$12) -> 0.058789 | D48: =SUMIFS(tblData[Q4 HPI YoY change],tblData[State],$B48,tblData[Year],D$12) -> 0.064644 | E48: =SUMIFS(tblData[Q4 HPI YoY change],tblData[State],$B48,tblData[Year],E$12) -> 0.122246 | F48: =SUMIFS(tblData[Q4 HPI YoY change],tblData[State],$B48,tblData[Year],F$12) -> 0.134625 | G48: =SUMIFS(tblData[Q4 HPI YoY change],tblData[State],$B48,tblData[Year],G$12) -> 0.082925 | H48: =SUMIFS(tblData[Q4 HPI YoY change],tblData[State],$B48,tblData[Year],H$12) -> 0.086376 | I48: =SUMIFS(tblData[Q4 HPI YoY change],tblData[State],$B48,tblData[Year],I$12) -> 0.067469 | J48: =SUMIFS(tblData[Q4 HPI YoY change],tblData[State],$B48,tblData[Year],J$12) -> 0.046511
B49: Oklahoma | C49: =SUMIFS(tblData[Q4 HPI YoY change],tblData[State],$B49,tblData[Year],C$12) -> 0.037235 | D49: =SUMIFS(tblData[Q4 HPI YoY change],tblData[State],$B49,tblData[Year],D$12) -> 0.042605 | E49: =SUMIFS(tblData[Q4 HPI YoY change],tblData[State],$B49,tblData[Year],E$12) -> 0.093826 | F49: =SUMIFS(tblData[Q4 HPI YoY change],tblData[State],$B49,tblData[Year],F$12) -> 0.160829 | G49: =SUMIFS(tblData[Q4 HPI YoY change],tblData[State],$B49,tblData[Year],G$12) -> 0.096581 | H49: =SUMIFS(tblData[Q4 HPI YoY change],tblData[State],$B49,tblData[Year],H$12) -> 0.042773 | I49: =SUMIFS(tblData[Q4 HPI YoY change],tblData[State],$B49,tblData[Year],I$12) -> 0.04244 | J49: =SUMIFS(tblData[Q4 HPI YoY change],tblData[State],$B49,tblData[Year],J$12) -> 0.033922
B50: Oregon | C50: =SUMIFS(tblData[Q4 HPI YoY change],tblData[State],$B50,tblData[Year],C$12) -> 0.05927 | D50: =SUMIFS(tblData[Q4 HPI YoY change],tblData[State],$B50,tblData[Year],D$12) -> 0.055978 | E50: =SUMIFS(tblData[Q4 HPI YoY change],tblData[State],$B50,tblData[Year],E$12) -> 0.116854 | F50: =SUMIFS(tblData[Q4 HPI YoY change],tblData[State],$B50,tblData[Year],F$12) -> 0.17237 | G50: =SUMIFS(tblData[Q4 HPI YoY change],tblData[State],$B50,tblData[Year],G$12) -> 0.033393 | H50: =SUMIFS(tblData[Q4 HPI YoY change],tblData[State],$B50,tblData[Year],H$12) -> 0.009689 | I50: =SUMIFS(tblData[Q4 HPI YoY change],tblData[State],$B50,tblData[Year],I$12) -> 0.031188 | J50: =SUMIFS(tblData[Q4 HPI YoY change],tblData[State],$B50,tblData[Year],J$12) -> 0.004637
B51: Pennsylvania | C51: =SUMIFS(tblData[Q4 HPI YoY change],tblData[State],$B51,tblData[Year],C$12) -> 0.045614 | D51: =SUMIFS(tblData[Q4 HPI YoY change],tblData[State],$B51,tblData[Year],D$12) -> 0.050269 | E51: =SUMIFS(tblData[Q4 HPI YoY change],tblData[State],$B51,tblData[Year],E$12) -> 0.109155 | F51: =SUMIFS(tblData[Q4 HPI YoY change],tblData[State],$B51,tblData[Year],F$12) -> 0.131398 | G51: =SUMIFS(tblData[Q4 HPI YoY change],tblData[State],$B51,tblData[Year],G$12) -> 0.072406 | H51: =SUMIFS(tblData[Q4 HPI YoY change],tblData[State],$B51,tblData[Year],H$12) -> 0.069564 | I51: =SUMIFS(tblData[Q4 HPI YoY change],tblData[State],$B51,tblData[Year],I$12) -> 0.06196 | J51: =SUMIFS(tblData[Q4 HPI YoY change],tblData[State],$B51,tblData[Year],J$12) -> 0.041619
B52: Rhode Island | C52: =SUMIFS(tblData[Q4 HPI YoY change],tblData[State],$B52,tblData[Year],C$12) -> 0.056786 | D52: =SUMIFS(tblData[Q4 HPI YoY change],tblData[State],$B52,tblData[Year],D$12) -> 0.063405 | E52: =SUMIFS(tblData[Q4 HPI YoY change],tblData[State],$B52,tblData[Year],E$12) -> 0.136532 | F52: =SUMIFS(tblData[Q4 HPI YoY change],tblData[State],$B52,tblData[Year],F$12) -> 0.157133 | G52: =SUMIFS(tblData[Q4 HPI YoY change],tblData[State],$B52,tblData[Year],G$12) -> 0.054224 | H52: =SUMIFS(tblData[Q4 HPI YoY change],tblData[State],$B52,tblData[Year],H$12) -> 0.136675 | I52: =SUMIFS(tblData[Q4 HPI YoY change],tblData[State],$B52,tblData[Year],I$12) -> 0.068333 | J52: =SUMIFS(tblData[Q4 HPI YoY change],tblData[State],$B52,tblData[Year],J$12) -> 0.047195
B53: South Carolina | C53: =SUMIFS(tblData[Q4 HPI YoY change],tblData[State],$B53,tblData[Year],C$12) -> 0.065364 | D53: =SUMIFS(tblData[Q4 HPI YoY change],tblData[State],$B53,tblData[Year],D$12) -> 0.057519 | E53: =SUMIFS(tblData[Q4 HPI YoY change],tblData[State],$B53,tblData[Year],E$12) -> 0.104525 | F53: =SUMIFS(tblData[Q4 HPI YoY change],tblData[State],$B53,tblData[Year],F$12) -> 0.210106 | G53: =SUMIFS(tblData[Q4 HPI YoY change],tblData[State],$B53,tblData[Year],G$12) -> 0.119781 | H53: =SUMIFS(tblData[Q4 HPI YoY change],tblData[State],$B53,tblData[Year],H$12) -> 0.086849 | I53: =SUMIFS(tblData[Q4 HPI YoY change],tblData[State],$B53,tblData[Year],I$12) -> 0.05299 | J53: =SUMIFS(tblData[Q4 HPI YoY change],tblData[State],$B53,tblData[Year],J$12) -> 0.020272
B54: South Dakota | C54: =SUMIFS(tblData[Q4 HPI YoY change],tblData[State],$B54,tblData[Year],C$12) -> 0.063862 | D54: =SUMIFS(tblData[Q4 HPI YoY change],tblData[State],$B54,tblData[Year],D$12) -> 0.038368 | E54: =SUMIFS(tblData[Q4 HPI YoY change],tblData[State],$B54,tblData[Year],E$12) -> 0.098978 | F54: =SUMIFS(tblData[Q4 HPI YoY change],tblData[State],$B54,tblData[Year],F$12) -> 0.179035 | G54: =SUMIFS(tblData[Q4 HPI YoY change],tblData[State],$B54,tblData[Year],G$12) -> 0.091635 | H54: =SUMIFS(tblData[Q4 HPI YoY change],tblData[State],$B54,tblData[Year],H$12) -> 0.064723 | I54: =SUMIFS(tblData[Q4 HPI YoY change],tblData[State],$B54,tblData[Year],I$12) -> 0.03718 | J54: =SUMIFS(tblData[Q4 HPI YoY change],tblData[State],$B54,tblData[Year],J$12) -> 0.021641
... B57: Utah | C57: =SUMIFS(tblData[Q4 HPI YoY change],tblData[State],$B57,tblData[Year],C$12) -> 0.094203 | D57: =SUMIFS(tblData[Q4 HPI YoY change],tblData[State],$B57,tblData[Year],D$12) -> 0.079274 | E57: =SUMIFS(tblData[Q4 HPI YoY change],tblData[State],$B57,tblData[Year],E$12) -> 0.15497 | F57: =SUMIFS(tblData[Q4 HPI YoY change],tblData[State],$B57,tblData[Year],F$12) -> 0.269298 | G57: =SUMIFS(tblData[Q4 HPI YoY change],tblData[State],$B57,tblData[Year],G$12) -> 0.031624 | H57: =SUMIFS(tblData[Q4 HPI YoY change],tblData[State],$B57,tblData[Year],H$12) -> 0.020512 | I57: =SUMIFS(tblData[Q4 HPI YoY change],tblData[State],$B57,tblData[Year],I$12) -> 0.046472 | J57: =SUMIFS(tblData[Q4 HPI YoY change],tblData[State],$B57,tblData[Year],J$12) -> 0.007795
B58: Vermont | C58: =SUMIFS(tblData[Q4 HPI YoY change],tblData[State],$B58,tblData[Year],C$12) -> 0.027406 | D58: =SUMIFS(tblData[Q4 HPI YoY change],tblData[State],$B58,tblData[Year],D$12) -> 0.043018 | E58: =SUMIFS(tblData[Q4 HPI YoY change],tblData[State],$B58,tblData[Year],E$12) -> 0.124187 | F58: =SUMIFS(tblData[Q4 HPI YoY change],tblData[State],$B58,tblData[Year],F$12) -> 0.182958 | G58: =SUMIFS(tblData[Q4 HPI YoY change],tblData[State],$B58,tblData[Year],G$12) -> 0.095565 | H58: =SUMIFS(tblData[Q4 HPI YoY change],tblData[State],$B58,tblData[Year],H$12) -> 0.107713 | I58: =SUMIFS(tblData[Q4 HPI YoY change],tblData[State],$B58,tblData[Year],I$12) -> 0.069192 | J58: =SUMIFS(tblData[Q4 HPI YoY change],tblData[State],$B58,tblData[Year],J$12) -> 0.039251 | N58: Source: FHFA HPI, purchase-only, index_sa (seasonally adjusted). Latest quarter: 2026 Q2. U.S. = FHFA quarterly U.S. index.
B59: Virginia | C59: =SUMIFS(tblData[Q4 HPI YoY change],tblData[State],$B59,tblData[Year],C$12) -> 0.044427 | D59: =SUMIFS(tblData[Q4 HPI YoY change],tblData[State],$B59,tblData[Year],D$12) -> 0.053181 | E59: =SUMIFS(tblData[Q4 HPI YoY change],tblData[State],$B59,tblData[Year],E$12) -> 0.105291 | F59: =SUMIFS(tblData[Q4 HPI YoY change],tblData[State],$B59,tblData[Year],F$12) -> 0.13443 | G59: =SUMIFS(tblData[Q4 HPI YoY change],tblData[State],$B59,tblData[Year],G$12) -> 0.082709 | H59: =SUMIFS(tblData[Q4 HPI YoY change],tblData[State],$B59,tblData[Year],H$12) -> 0.071558 | I59: =SUMIFS(tblData[Q4 HPI YoY change],tblData[State],$B59,tblData[Year],I$12) -> 0.058691 | J59: =SUMIFS(tblData[Q4 HPI YoY change],tblData[State],$B59,tblData[Year],J$12) -> 0.037856
B60: Washington | C60: =SUMIFS(tblData[Q4 HPI YoY change],tblData[State],$B60,tblData[Year],C$12) -> 0.076895 | D60: =SUMIFS(tblData[Q4 HPI YoY change],tblData[State],$B60,tblData[Year],D$12) -> 0.078008 | E60: =SUMIFS(tblData[Q4 HPI YoY change],tblData[State],$B60,tblData[Year],E$12) -> 0.140243 | F60: =SUMIFS(tblData[Q4 HPI YoY change],tblData[State],$B60,tblData[Year],F$12) -> 0.192995 | G60: =SUMIFS(tblData[Q4 HPI YoY change],tblData[State],$B60,tblData[Year],G$12) -> 0.030872 | H60: =SUMIFS(tblData[Q4 HPI YoY change],tblData[State],$B60,tblData[Year],H$12) -> 0.03426 | I60: =SUMIFS(tblData[Q4 HPI YoY change],tblData[State],$B60,tblData[Year],I$12) -> 0.030393 | J60: =SUMIFS(tblData[Q4 HPI YoY change],tblData[State],$B60,tblData[Year],J$12) -> 0.022083
B61: West Virginia | C61: =SUMIFS(tblData[Q4 HPI YoY change],tblData[State],$B61,tblData[Year],C$12) -> 0.001071 | D61: =SUMIFS(tblData[Q4 HPI YoY change],tblData[State],$B61,tblData[Year],D$12) -> 0.073867 | E61: =SUMIFS(tblData[Q4 HPI YoY change],tblData[State],$B61,tblData[Year],E$12) -> 0.057556 | F61: =SUMIFS(tblData[Q4 HPI YoY change],tblData[State],$B61,tblData[Year],F$12) -> 0.123191 | G61: =SUMIFS(tblData[Q4 HPI YoY change],tblData[State],$B61,tblData[Year],G$12) -> 0.05829 | H61: =SUMIFS(tblData[Q4 HPI YoY change],tblData[State],$B61,tblData[Year],H$12) -> 0.122875 | I61: =SUMIFS(tblData[Q4 HPI YoY change],tblData[State],$B61,tblData[Year],I$12) -> 0.033653 | J61: =SUMIFS(tblData[Q4 HPI YoY change],tblData[State],$B61,tblData[Year],J$12) -> 0.004469
B62: Wisconsin | C62: =SUMIFS(tblData[Q4 HPI YoY change],tblData[State],$B62,tblData[Year],C$12) -> 0.069702 | D62: =SUMIFS(tblData[Q4 HPI YoY change],tblData[State],$B62,tblData[Year],D$12) -> 0.064653 | E62: =SUMIFS(tblData[Q4 HPI YoY change],tblData[State],$B62,tblData[Year],E$12) -> 0.105036 | F62: =SUMIFS(tblData[Q4 HPI YoY change],tblData[State],$B62,tblData[Year],F$12) -> 0.133756 | G62: =SUMIFS(tblData[Q4 HPI YoY change],tblData[State],$B62,tblData[Year],G$12) -> 0.095627 | H62: =SUMIFS(tblData[Q4 HPI YoY change],tblData[State],$B62,tblData[Year],H$12) -> 0.086907 | I62: =SUMIFS(tblData[Q4 HPI YoY change],tblData[State],$B62,tblData[Year],I$12) -> 0.067528 | J62: =SUMIFS(tblData[Q4 HPI YoY change],tblData[State],$B62,tblData[Year],J$12) -> 0.056952
B63: Wyoming | C63: =SUMIFS(tblData[Q4 HPI YoY change],tblData[State],$B63,tblData[Year],C$12) -> 0.036058 | D63: =SUMIFS(tblData[Q4 HPI YoY change],tblData[State],$B63,tblData[Year],D$12) -> 0.061312 | E63: =SUMIFS(tblData[Q4 HPI YoY change],tblData[State],$B63,tblData[Year],E$12) -> 0.081801 | F63: =SUMIFS(tblData[Q4 HPI YoY change],tblData[State],$B63,tblData[Year],F$12) -> 0.166941 | G63: =SUMIFS(tblData[Q4 HPI YoY change],tblData[State],$B63,tblData[Year],G$12) -> 0.073942 | H63: =SUMIFS(tblData[Q4 HPI YoY change],tblData[State],$B63,tblData[Year],H$12) -> 0.026732 | I63: =SUMIFS(tblData[Q4 HPI YoY change],tblData[State],$B63,tblData[Year],I$12) -> 0.074831 | J63: =SUMIFS(tblData[Q4 HPI YoY change],tblData[State],$B63,tblData[Year],J$12) -> 0.032775
B65: Source: FHFA HPI, Q4 vs. prior-year Q4, 2018-2025 (latest available quarter: 2026 Q2). Orange = price decline, purple = price increase. Price trend = these values; loans trend = CFPB HMDA total originations, 2018-2025.
B66: Built from public FHFA and CFPB data. Not an official Fannie Mae, FHFA, or CFPB product.

Sheet Data
A1: State code | B1: State | C1: Region | D1: Division | E1: Year | F1: Purchase loans | G1: Purchase volume | H1: Refinance loans | I1: Refinance volume | J1: Cash-out refi loans | K1: Cash-out refi volume | L1: Total loans | M1: Total dollar volume | N1: Avg loan size | O1: Q4 HPI YoY change
A2: AL | B2: Alabama | C2: South | D2: East South Central | E2: 2018 | F2: 64977 | G2: 12441015000 | H2: 15735 | I2: 2968945000 | J2: 12698 | K2: 2121790000 | L2: 93410 | M2: 17531750000 | N2: 187686.01 | O2: 0.046723
A3: AL | B3: Alabama | C3: South | D3: East South Central | E3: 2019 | F3: 69028 | G3: 14062010000 | H3: 25121 | I3: 5927115000 | J3: 15137 | K3: 2888135000 | L3: 109286 | M3: 22877260000 | N3: 209333.86 | O3: 0.065616
A4: AL | B4: Alabama | C4: South | D4: East South Central | E4: 2020 | F4: 80056 | G4: 17433210000 | H4: 72194 | I4: 16409490000 | J4: 21558 | K4: 4653220000 | L4: 173808 | M4: 38495920000 | N4: 221485.32 | O4: 0.113352
A5: AL | B5: Alabama | C5: South | D5: East South Central | E5: 2021 | F5: 88540 | G5: 21757490000 | H5: 64466 | I5: 14136150000 | J5: 31624 | K5: 6599270000 | L5: 184630 | M5: 42492910000 | N5: 230151.71 | O5: 0.170088
A6: AL | B6: Alabama | C6: South | D6: East South Central | E6: 2022 | F6: 73500 | G6: 20324570000 | H6: 16492 | I6: 4012090000 | J6: 21438 | K6: 4454040000 | L6: 111430 | M6: 28790700000 | N6: 258374.76 | O6: 0.09743
A7: AL | B7: Alabama | C7: South | D7: East South Central | E7: 2023 | F7: 59342 | G7: 15618320000 | H7: 8991 | I7: 2304845000 | J7: 10776 | K7: 2255870000 | L7: 79109 | M7: 20179035000 | N7: 255078.88 | O7: 0.041433
A8: AL | B8: Alabama | C8: South | D8: East South Central | E8: 2024 | F8: 61667 | G8: 16085195000 | H8: 13241 | I8: 3568665000 | J8: 12337 | K8: 2500695000 | L8: 87245 | M8: 22154555000 | N8: 253934.95 | O8: 0.048609
A9: AL | B9: Alabama | C9: South | D9: East South Central | E9: 2025 | F9: 63509 | G9: 17647305000 | H9: 17724 | I9: 5515480000 | J9: 15370 | K9: 3224830000 | L9: 96603 | M9: 26387615000 | N9: 273155.23 | O9: 0.024969
A10: AK | B10: Alaska | C10: West | D10: Pacific | E10: 2018 | F10: 8999 | G10: 2604125000 | H10: 1186 | I10: 287780000 | J10: 2122 | K10: 481150000 | L10: 12307 | M10: 3373055000 | N10: 274076.14 | O10: 0.013034
A11: AK | B11: Alaska | C11: West | D11: Pacific | E11: 2019 | F11: 9226 | G11: 2639130000 | H11: 3135 | I11: 929845000 | J11: 2086 | K11: 509440000 | L11: 14447 | M11: 4078415000 | N11: 282301.86 | O11: 0.040887
A12: AK | B12: Alaska | C12: West | D12: Pacific | E12: 2020 | F12: 10336 | G12: 3157330000 | H12: 11701 | I12: 3422115000 | J12: 3250 | K12: 844870000 | L12: 25287 | M12: 7424315000 | N12: 293602.05 | O12: 0.085273
A13: AK | B13: Alaska | C13: West | D13: Pacific | E13: 2021 | F13: 11892 | G13: 3938960000 | H13: 11157 | I13: 3116815000 | J13: 3983 | K13: 1056315000 | L13: 27032 | M13: 8112090000 | N13: 300092.11 | O13: 0.104741
... A409: WY | B409: Wyoming | C409: West | D409: Mountain | E409: 2025 | F409: 7320 | G409: 2578610000 | H409: 1900 | I409: 790450000 | J409: 2066 | K409: 502770000 | L409: 11286 | M409: 3871830000 | N409: 343064.86 | O409: 0.032775
A411: Sources: CFPB HMDA (originated loans, 2018-2025); FHFA HPI purchase-only, index_nsa (Q4 vs prior-year Q4).
A412: Built from public FHFA and CFPB data. Not an official Fannie Mae, FHFA, or CFPB product.

Sheet Pivot
A1: PivotTable: loans and average loan size by Census region and year
A2: Source: CFPB HMDA originated loans, 2018-2025. Average loan size = total dollar volume / total loans (calculated field). Right-click > Refresh after you edit the Data table.
B3: Year
B4: Loans (count) | J4: Average loan size | R4: Total Loans (count) | S4: Total Average loan size
A5: Region | B5: 2018 | C5: 2019 | D5: 2020 | E5: 2021 | F5: 2022 | G5: 2023 | H5: 2024 | I5: 2025 | J5: 2018 | K5: 2019 | L5: 2020 | M5: 2021 | N5: 2022 | O5: 2023 | P5: 2024 | Q5: 2025
A6: Midwest | B6: 1426742 | C6: 1730055 | D6: 2863346 | E6: 2825134 | F6: 1458566 | G6: 999757 | H6: 1106374 | I6: 1248891 | J6: 196729.92 | K6: 214206.35 | L6: 224584.95 | M6: 228750.68 | N6: 255069.75 | O6: 255086.94 | P6: 265744.41 | Q6: 291378.27 | R6: 13658865 | S6: 236151.45
A7: Northeast | B7: 933635 | C7: 1110121 | D7: 1766374 | E7: 1915895 | F7: 978278 | G7: 619449 | H7: 671115 | I7: 766890 | J7: 323474.64 | K7: 349444.99 | L7: 344370.46 | M7: 359118.27 | N7: 419369.28 | O7: 392737.8 | P7: 415569.51 | Q7: 451440.06 | R7: 8761757 | S7: 372630.05
A8: South | B8: 2505602 | C8: 3005961 | D8: 4860924 | E8: 5162525 | F8: 2887047 | G8: 1984330 | H8: 2140206 | I8: 2330693 | J8: 246357.16 | K8: 264180.5 | L8: 275635.56 | M8: 290291.71 | N8: 338104.23 | O8: 333859.85 | P8: 348042.31 | Q8: 359161.57 | R8: 24877288 | S8: 300292.36
A9: West | B9: 1766599 | C9: 2438576 | D9: 4278858 | E9: 4180730 | F9: 1670588 | G9: 916652 | H9: 1068010 | I9: 1222236 | J9: 374506.49 | K9: 401752.61 | L9: 388385.35 | M9: 426884.66 | N9: 509611.8 | O9: 499956.83 | P9: 523120.35 | Q9: 544384.03 | R9: 17542249 | S9: 434467.87
A10: Grand Total | B10: 6632578 | C10: 8284713 | D10: 13769502 | E10: 14084284 | F10: 6994479 | G10: 4520188 | H10: 4985705 | I10: 5568710 | J10: 280670.03 | K10: 305663.64 | L10: 308873.97 | M10: 327855.64 | N10: 373118.56 | O10: 358188.76 | P10: 376373.58 | Q10: 397321.05 | R10: 64840159 | S10: 332856.34
A37: Source: CFPB HMDA, originated loans 2018-2025 (latest HMDA year: 2025).
A38: Built from public FHFA and CFPB data. Not an official Fannie Mae, FHFA, or CFPB product.

Sheet Notes
A1: Notes and sources
A3: Source | B3: Link | C3: Used for
A4: FHFA House Price Index (HPI) master file | B4: https://www.fhfa.gov/hpi/download/monthly/hpi_master.csv | C4: Heat map, home price cards and charts (traditional, purchase-only; index_nsa for year over year, index_sa for levels and since 2019 Q4)
A5: CFPB HMDA Data Browser API | B5: https://ffiec.cfpb.gov/v2/data-browser-api/view/aggregations | C5: Loans and dollar volume by state, year, and loan purpose (originated loans only)
A6: U.S. Census Bureau regions and divisions | B6: https://www2.census.gov/geo/pdfs/maps-data/maps/reference/us_regdiv.pdf | C6: Region and division for each state
A9: Item | B9: Definition
A10: Latest period | B10: Latest complete HPI quarter: 2026 Q2. HMDA years: 2018-2025.
A11: HPI | B11: The HPI is an index, not a price. 1991 Q1 = 100 (January 1991 = 100 for monthly data).
A12: Q4 HPI YoY change | B12: State Q4 index_nsa divided by the same state's Q4 index_nsa one year earlier, minus 1.
A13: State YoY change (cards) | B13: State index_nsa for 2026 Q2 compared with the same quarter one year earlier.
A14: U.S. YoY change | B14: FHFA's quarterly U.S. index_nsa for 2026 Q2, compared with the same quarter one year earlier.
A15: Change since 2019 Q4 | B15: index_sa (seasonally adjusted) for 2026 Q2 compared with 2019 Q4, the last quarter before the pandemic. The two quarters are different seasons, so the seasonally adjusted index is used.
A16: HPI trend chart | B16: index_sa (seasonally adjusted), because the chart compares many different quarters.
A17: Loans | B17: HMDA originated loans (action taken = 1). Purposes: Home purchase (1), Refinance (31), Cash-out refinance (32).
A18: Avg loan size | B18: Total dollar volume / total loans for the three loan purposes. The PivotTable uses the calculated field 'Weighted loan size' (= sum of dollar volume / sum of loans).
A19: Sheets | B19: Dashboard (state drop-down, KPI cards, charts, heat map, sparklines); Data (tblData table); Pivot (PivotTable and PivotChart); Calc (formula helpers for the dashboard).
A20: Rebuild | B20: Run: .venv/bin/python analysis/build_workbook.py (reads data/ only).
A22: Facts from the data only. No forecasts and no investment advice.
A23: Built from public FHFA and CFPB data. Not an official Fannie Mae, FHFA, or CFPB product.

Sheet Calc
A1: State code | B1: State | C1: Region | D1: HPI YoY 2026 Q2 | E1: Change since 2019 Q4 | F1: HPI 2026 Q2 | H1: Metric | I1: Value | P1: Quarter | Q1: U.S. | R1: Selected state | S1: AL | T1: AK | U1: AZ | V1: AR | W1: CA | X1: CO | Y1: CT | Z1: DE | AA1: DC | AB1: FL | AC1: GA | AD1: HI | AE1: ID | AF1: IL | AG1: IN | AH1: IA | AI1: KS | AJ1: KY | AK1: LA | AL1: ME | AM1: MD | AN1: MA | AO1: MI | AP1: MN | AQ1: MS | AR1: MO | AS1: MT | AT1: NE | AU1: NV | AV1: NH | AW1: NJ | AX1: NM | AY1: NY | AZ1: NC | BA1: ND | BB1: OH | BC1: OK | BD1: OR | BE1: PA | BF1: RI | BG1: SC | BH1: SD | BI1: TN | BJ1: TX | BK1: UT | BL1: VT | BM1: VA | BN1: WA | BO1: WV | BP1: WI | BQ1: WY
A2: AL | B2: Alabama | C2: South | D2: 0.027938239 | E2: 0.62224237 | F2: 375.76 | H2: U.S. HPI YoY (2026 Q2) | I2: 0.020891943 | P2: 2015 Q1 | Q2: 209 | R2: =INDEX($S$2:$BQ$2,MATCH($I$7,$S$1:$BQ$1,0)) -> 219.68 | S2: 185.24 | T2: 241.18 | U2: 240.4 | V2: 187.74 | W2: 218.62 | X2: 327.52 | Y2: 160.47 | Z2: 181.86 | AA2: 418.02 | AB2: 225.16 | AC2: 185.52 | AD2: 213.16 | AE2: 229.53 | AF2: 176.55 | AG2: 169.97 | AH2: 210.62 | AI2: 203.57 | AJ2: 197.58 | AK2: 248.63 | AL2: 204.18 | AM2: 217.12 | AN2: 231.09 | AO2: 174.64 | AP2: 226.73 | AQ2: 184.32 | AR2: 191.59 | AS2: 327.79 | AT2: 215.83 | AU2: 180.32 | AV2: 206.95 | AW2: 210.3 | AX2: 210.62 | AY2: 203.58 | AZ2: 190.3 | BA2: 293.74 | BB2: 162.59 | BC2: 212.33 | BD2: 309.66 | BE2: 190 | BF2: 186.37 | BG2: 194.63 | BH2: 247.15 | BI2: 204.47 | BJ2: 226.71 | BK2: 300.13 | BL2: 203.95 | BM2: 219.68 | BN2: 252.04 | BO2: 195.42 | BP2: 211.44 | BQ2: 313.14
A3: AK | B3: Alaska | C3: West | D3: 0.082760069 | E3: 0.53656331 | F3: 407.85 | H3: U.S. change since 2019 Q4 | I3: 0.60492872 | P3: 2015 Q2 | Q3: 211.68 | R3: =INDEX($S$3:$BQ$3,MATCH($I$7,$S$1:$BQ$1,0)) -> 220.63 | S3: 188.57 | T3: 240.72 | U3: 243.62 | V3: 191.87 | W3: 221.64 | X3: 334.54 | Y3: 161.14 | Z3: 182.68 | AA3: 429.13 | AB3: 229.59 | AC3: 188.15 | AD3: 213.9 | AE3: 237.05 | AF3: 178.21 | AG3: 171.59 | AH3: 212.39 | AI3: 204.87 | AJ3: 199.01 | AK3: 250.55 | AL3: 211.03 | AM3: 219.28 | AN3: 234.51 | AO3: 178.55 | AP3: 232.49 | AQ3: 185.05 | AR3: 194.73 | AS3: 329.91 | AT3: 217.08 | AU3: 183.56 | AV3: 207.43 | AW3: 209.16 | AX3: 211.45 | AY3: 204.6 | AZ3: 192.43 | BA3: 293.13 | BB3: 164.39 | BC3: 211.56 | BD3: 319.13 | BE3: 192.19 | BF3: 187.28 | BG3: 196.65 | BH3: 249.1 | BI3: 205.71 | BJ3: 230.64 | BK3: 302.4 | BL3: 210.98 | BM3: 220.63 | BN3: 258.04 | BO3: 198.94 | BP3: 212.47 | BQ3: 312.27
A4: AZ | B4: Arizona | C4: West | D4: 0.0052214238 | E4: 0.64588071 | F4: 564.57 | H4: U.S. avg loan size (2025) | I4: =SUMIFS(tblData[Total dollar volume],tblData[Year],2025)/SUMIFS(tblData[Total loans],tblData[Year],2025) -> 397321.05 | P4: 2015 Q3 | Q4: 214.25 | R4: =INDEX($S$4:$BQ$4,MATCH($I$7,$S$1:$BQ$1,0)) -> 221.96 | S4: 188.85 | T4: 240.9 | U4: 249.41 | V4: 194.58 | W4: 225.38 | X4: 344.18 | Y4: 160.49 | Z4: 184.89 | AA4: 445.61 | AB4: 234.72 | AC4: 191.51 | AD4: 215.3 | AE4: 237.79 | AF4: 179.01 | AG4: 172.34 | AH4: 213.72 | AI4: 207.2 | AJ4: 200.64 | AK4: 252.93 | AL4: 208.75 | AM4: 220.01 | AN4: 236.41 | AO4: 179.26 | AP4: 234.2 | AQ4: 185.91 | AR4: 197.37 | AS4: 331.78 | AT4: 220.94 | AU4: 190.2 | AV4: 210.62 | AW4: 210.82 | AX4: 217.4 | AY4: 206.63 | AZ4: 195.82 | BA4: 295.05 | BB4: 165.63 | BC4: 214.36 | BD4: 327.59 | BE4: 194.08 | BF4: 189.21 | BG4: 196.15 | BH4: 251.11 | BI4: 209.2 | BJ4: 233.92 | BK4: 307.91 | BL4: 210.76 | BM4: 221.96 | BN4: 263.55 | BO4: 199 | BP4: 213.29 | BQ4: 316.71
A5: AR | B5: Arkansas | C5: South | D5: 0.010897698 | E5: 0.64149521 | F5: 370.19 | P5: 2015 Q4 | Q5: 217.28 | R5: =INDEX($S$5:$BQ$5,MATCH($I$7,$S$1:$BQ$1,0)) -> 224.43 | S5: 189.79 | T5: 244.77 | U5: 253.21 | V5: 195.28 | W5: 229.98 | X5: 349.66 | Y5: 161.03 | Z5: 187.86 | AA5: 437.46 | AB5: 240.32 | AC5: 193.63 | AD5: 220.73 | AE5: 247.79 | AF5: 179.8 | AG5: 174.31 | AH5: 217.74 | AI5: 207.94 | AJ5: 204.9 | AK5: 254.42 | AL5: 210.29 | AM5: 219.93 | AN5: 239 | AO5: 183.11 | AP5: 238.52 | AQ5: 189.63 | AR5: 199.95 | AS5: 335.36 | AT5: 222 | AU5: 193.54 | AV5: 212.11 | AW5: 211.45 | AX5: 214.38 | AY5: 207.16 | AZ5: 198.25 | BA5: 297.16 | BB5: 167.87 | BC5: 216.54 | BD5: 336.88 | BE5: 195.26 | BF5: 192.07 | BG5: 203.24 | BH5: 254.63 | BI5: 211.58 | BJ5: 237.36 | BK5: 315.75 | BL5: 207.88 | BM5: 224.43 | BN5: 272.17 | BO5: 203.77 | BP5: 216.53 | BQ5: 316.25
A6: CA | B6: California | C6: West | D6: -0.0028963666 | E6: 0.43404723 | F6: 417.15 | H6: Selected state | I6: =Dashboard!$C$4 -> Virginia | P6: 2016 Q1 | Q6: 219.95 | R6: =INDEX($S$6:$BQ$6,MATCH($I$7,$S$1:$BQ$1,0)) -> 226.61 | S6: 191.8 | T6: 245.15 | U6: 257.58 | V6: 195.83 | W6: 233.56 | X6: 359.11 | Y6: 160.71 | Z6: 187.9 | AA6: 434.79 | AB6: 245.38 | AC6: 195.89 | AD6: 220.77 | AE6: 250.11 | AF6: 180.66 | AG6: 175.65 | AH6: 218.45 | AI6: 212.67 | AJ6: 206.19 | AK6: 256.94 | AL6: 213.35 | AM6: 224.56 | AN6: 242.03 | AO6: 185.38 | AP6: 241.64 | AQ6: 189.36 | AR6: 204.4 | AS6: 339.44 | AT6: 221.82 | AU6: 198.83 | AV6: 212.64 | AW6: 211.98 | AX6: 214.5 | AY6: 208.52 | AZ6: 200.41 | BA6: 297.9 | BB6: 169.44 | BC6: 215.27 | BD6: 346.17 | BE6: 196.63 | BF6: 193.17 | BG6: 205.04 | BH6: 260.83 | BI6: 215.83 | BJ6: 241.5 | BK6: 321.94 | BL6: 206.88 | BM6: 226.61 | BN6: 277.79 | BO6: 200.17 | BP6: 219.5 | BQ6: 316.74
A7: CO | B7: Colorado | C7: West | D7: -0.0060726111 | E7: 0.41136459 | F7: 674.35 | H7: State code | I7: =INDEX($A$2:$A$52,MATCH($I$6,$B$2:$B$52,0)) -> VA | P7: 2016 Q2 | Q7: 223.11 | R7: =INDEX($S$7:$BQ$7,MATCH($I$7,$S$1:$BQ$1,0)) -> 228.25 | S7: 193.68 | T7: 247.5 | U7: 262.78 | V7: 197.56 | W7: 237.65 | X7: 367.69 | Y7: 161.23 | Z7: 189.32 | AA7: 459.37 | AB7: 251.1 | AC7: 200.28 | AD7: 217.47 | AE7: 253.23 | AF7: 182.65 | AG7: 179.12 | AH7: 220.73 | AI7: 215.07 | AJ7: 208.16 | AK7: 258.15 | AL7: 215.35 | AM7: 227.03 | AN7: 244.81 | AO7: 187.87 | AP7: 244.14 | AQ7: 190.07 | AR7: 203.62 | AS7: 341.92 | AT7: 226.83 | AU7: 202.56 | AV7: 217.45 | AW7: 214.91 | AX7: 219.88 | AY7: 212.1 | AZ7: 203.12 | BA7: 299.49 | BB7: 171.7 | BC7: 217.45 | BD7: 354.18 | BE7: 198.43 | BF7: 196.17 | BG7: 206.44 | BH7: 260.11 | BI7: 218.86 | BJ7: 245.53 | BK7: 327.59 | BL7: 209.6 | BM7: 228.25 | BN7: 284.25 | BO7: 203.54 | BP7: 222.37 | BQ7: 316.63
A8: CT | B8: Connecticut | C8: Northeast | D8: 0.045917875 | E8: 0.83055125 | F8: 319.12 | P8: 2016 Q3 | Q8: 226.44 | R8: =INDEX($S$8:$BQ$8,MATCH($I$7,$S$1:$BQ$1,0)) -> 230.76 | S8: 195.93 | T8: 247.06 | U8: 265.52 | V8: 199.08 | W8: 241.19 | X8: 377.69 | Y8: 161.33 | Z8: 190 | AA8: 453.3 | AB8: 257.98 | AC8: 203.67 | AD8: 219.68 | AE8: 261.52 | AF8: 185.31 | AG8: 181.78 | AH8: 223.7 | AI8: 216.86 | AJ8: 211.66 | AK8: 259.06 | AL8: 218.14 | AM8: 226.64 | AN8: 249.04 | AO8: 191.55 | AP8: 248.7 | AQ8: 191.57 | AR8: 207.39 | AS8: 344.17 | AT8: 229.77 | AU8: 204.99 | AV8: 218.49 | AW8: 215.92 | AX8: 217.94 | AY8: 213.69 | AZ8: 206.81 | BA8: 299.84 | BB8: 174.19 | BC8: 218.29 | BD8: 361.97 | BE8: 200.98 | BF8: 199.77 | BG8: 209.38 | BH8: 265.91 | BI8: 223.03 | BJ8: 250.36 | BK8: 334.68 | BL8: 213.27 | BM8: 230.76 | BN8: 291.79 | BO8: 202.62 | BP8: 225.01 | BQ8: 317.32
A9: DE | B9: Delaware | C9: South | D9: 0.032301003 | E9: 0.60793746 | F9: 347.62 | H9: Year | I9: Home purchase | J9: Refinance | K9: Cash-out refinance | L9: Avg loan size | M9: State Q4 HPI YoY | N9: U.S. Q4 HPI YoY | P9: 2016 Q4 | Q9: 229.93 | R9: =INDEX($S$9:$BQ$9,MATCH($I$7,$S$1:$BQ$1,0)) -> 232.67 | S9: 197.92 | T9: 247.32 | U9: 271.62 | V9: 199.95 | W9: 245.74 | X9: 387.13 | Y9: 162.9 | Z9: 189.78 | AA9: 469.62 | AB9: 262.88 | AC9: 206.93 | AD9: 230.73 | AE9: 265.03 | AF9: 187.77 | AG9: 184.23 | AH9: 225.07 | AI9: 220.89 | AJ9: 212.71 | AK9: 264.71 | AL9: 225.53 | AM9: 231.16 | AN9: 252.89 | AO9: 194.75 | AP9: 252.02 | AQ9: 194.38 | AR9: 210.51 | AS9: 357.32 | AT9: 231.07 | AU9: 211.55 | AV9: 221.32 | AW9: 217.15 | AX9: 222.31 | AY9: 217.02 | AZ9: 210.22 | BA9: 301.88 | BB9: 176.5 | BC9: 220 | BD9: 371.82 | BE9: 202.92 | BF9: 203.09 | BG9: 213.43 | BH9: 267.01 | BI9: 226.96 | BJ9: 253.26 | BK9: 340.79 | BL9: 212.36 | BM9: 232.67 | BN9: 299.74 | BO9: 202.49 | BP9: 228.66 | BQ9: 318.02
A10: DC | B10: District of Columbia | C10: South | D10: 0.015349385 | E10: 0.08585904 | F10: 604.4 | H10: 2018 | I10: =SUMIFS(tblData[Purchase loans],tblData[State code],$I$7,tblData[Year],$H10) -> 126055 | J10: =SUMIFS(tblData[Refinance loans],tblData[State code],$I$7,tblData[Year],$H10) -> 28560 | K10: =SUMIFS(tblData[Cash-out refi loans],tblData[State code],$I$7,tblData[Year],$H10) -> 29044 | L10: =SUMIFS(tblData[Total dollar volume],tblData[State code],$I$7,tblData[Year],$H10)/SUMIFS(tblData[Total loans],tblData[State code],$I$7,tblData[Year],$H10) -> 305832.68 | M10: =SUMIFS(tblData[Q4 HPI YoY change],tblData[State code],$I$7,tblData[Year],$H10) -> 0.044427 | N10: 0.054392447 | P10: 2017 Q1 | Q10: 232.89 | R10: =INDEX($S$10:$BQ$10,MATCH($I$7,$S$1:$BQ$1,0)) -> 234.11 | S10: 199.53 | T10: 249.63 | U10: 276.96 | V10: 203.13 | W10: 250.35 | X10: 394.22 | Y10: 163.32 | Z10: 190.17 | AA10: 473.6 | AB10: 267.95 | AC10: 210.14 | AD10: 223.46 | AE10: 272.82 | AF10: 189.7 | AG10: 185.64 | AH10: 227.74 | AI10: 221.3 | AJ10: 216.71 | AK10: 263.99 | AL10: 224.33 | AM10: 232.11 | AN10: 255.63 | AO10: 198.77 | AP10: 256.57 | AQ10: 194.4 | AR10: 211.76 | AS10: 356.56 | AT10: 236.19 | AU10: 214.39 | AV10: 229.62 | AW10: 217.59 | AX10: 225.51 | AY10: 218.63 | AZ10: 211.26 | BA10: 299.3 | BB10: 178.99 | BC10: 223.13 | BD10: 374.99 | BE10: 204.61 | BF10: 206.64 | BG10: 215.3 | BH10: 269.71 | BI10: 230.42 | BJ10: 257.39 | BK10: 347.8 | BL10: 224.82 | BM10: 234.11 | BN10: 307.33 | BO10: 201.58 | BP10: 231.7 | BQ10: 318.99
A11: FL | B11: Florida | C11: South | D11: 0.0091404336 | E11: 0.69699318 | F11: 547.45 | H11: 2019 | I11: =SUMIFS(tblData[Purchase loans],tblData[State code],$I$7,tblData[Year],$H11) -> 134404 | J11: =SUMIFS(tblData[Refinance loans],tblData[State code],$I$7,tblData[Year],$H11) -> 68456 | K11: =SUMIFS(tblData[Cash-out refi loans],tblData[State code],$I$7,tblData[Year],$H11) -> 37247 | L11: =SUMIFS(tblData[Total dollar volume],tblData[State code],$I$7,tblData[Year],$H11)/SUMIFS(tblData[Total loans],tblData[State code],$I$7,tblData[Year],$H11) -> 333847.06 | M11: =SUMIFS(tblData[Q4 HPI YoY change],tblData[State code],$I$7,tblData[Year],$H11) -> 0.053181 | N11: 0.054389722 | P11: 2017 Q2 | Q11: 236.86 | R11: =INDEX($S$11:$BQ$11,MATCH($I$7,$S$1:$BQ$1,0)) -> 237.65 | S11: 201.77 | T11: 247.25 | U11: 282.99 | V11: 203.27 | W11: 255.41 | X11: 404.33 | Y11: 164.42 | Z11: 191.47 | AA11: 475 | AB11: 273.66 | AC11: 214.03 | AD11: 237.06 | AE11: 278.65 | AF11: 189.16 | AG11: 187.92 | AH11: 229.46 | AI11: 225.12 | AJ11: 220.76 | AK11: 266.72 | AL11: 227.89 | AM11: 234.56 | AN11: 261.63 | AO11: 202.45 | AP11: 260.36 | AQ11: 195.51 | AR11: 216.81 | AS11: 362.08 | AT11: 240.63 | AU11: 218.04 | AV11: 229.29 | AW11: 221.12 | AX11: 226.64 | AY11: 221.3 | AZ11: 217.4 | BA11: 303.29 | BB11: 181.57 | BC11: 225.14 | BD11: 384.17 | BE11: 207.14 | BF11: 211.1 | BG11: 218.06 | BH11: 275.81 | BI11: 235.43 | BJ11: 263.49 | BK11: 356.53 | BL11: 217.73 | BM11: 237.65 | BN11: 316.59 | BO11: 203.57 | BP11: 235.64 | BQ11: 321.79
A12: GA | B12: Georgia | C12: South | D12: 0.018330132 | E12: 0.68431466 | F12: 425.66 | H12: 2020 | I12: =SUMIFS(tblData[Purchase loans],tblData[State code],$I$7,tblData[Year],$H12) -> 148659 | J12: =SUMIFS(tblData[Refinance loans],tblData[State code],$I$7,tblData[Year],$H12) -> 244471 | K12: =SUMIFS(tblData[Cash-out refi loans],tblData[State code],$I$7,tblData[Year],$H12) -> 56034 | L12: =SUMIFS(tblData[Total dollar volume],tblData[State code],$I$7,tblData[Year],$H12)/SUMIFS(tblData[Total loans],tblData[State code],$I$7,tblData[Year],$H12) -> 341921.06 | M12: =SUMIFS(tblData[Q4 HPI YoY change],tblData[State code],$I$7,tblData[Year],$H12) -> 0.105291 | N12: 0.11033159 | P12: 2017 Q3 | Q12: 240.44 | R12: =INDEX($S$12:$BQ$12,MATCH($I$7,$S$1:$BQ$1,0)) -> 240.19 | S12: 204.15 | T12: 250.81 | U12: 288.75 | V12: 206.26 | W12: 260.77 | X12: 410.97 | Y12: 166.15 | Z12: 194.27 | AA12: 487.2 | AB12: 278.26 | AC12: 216.93 | AD12: 247.11 | AE12: 284.29 | AF12: 191.2 | AG12: 190.71 | AH12: 231.63 | AI12: 227.05 | AJ12: 223.76 | AK12: 268.42 | AL12: 232.62 | AM12: 237.66 | AN12: 265.42 | AO12: 205.92 | AP12: 263.63 | AQ12: 198.88 | AR12: 218.37 | AS12: 367.42 | AT12: 242.68 | AU12: 225.9 | AV12: 233.13 | AW12: 224.81 | AX12: 229.23 | AY12: 225.71 | AZ12: 219.79 | BA12: 304.79 | BB12: 184.26 | BC12: 227.73 | BD12: 390.38 | BE12: 209.64 | BF12: 211.84 | BG12: 222.95 | BH12: 277.65 | BI12: 239.28 | BJ12: 266.6 | BK12: 365.83 | BL12: 218.72 | BM12: 240.19 | BN12: 324.08 | BO12: 203.41 | BP12: 238.95 | BQ12: 323.65
A13: HI | B13: Hawaii | C13: West | D13: 0.059349553 | E13: 0.60347389 | F13: 420.96 | H13: 2021 | I13: =SUMIFS(tblData[Purchase loans],tblData[State code],$I$7,tblData[Year],$H13) -> 167028 | J13: =SUMIFS(tblData[Refinance loans],tblData[State code],$I$7,tblData[Year],$H13) -> 198915 | K13: =SUMIFS(tblData[Cash-out refi loans],tblData[State code],$I$7,tblData[Year],$H13) -> 81112 | L13: =SUMIFS(tblData[Total dollar volume],tblData[State code],$I$7,tblData[Year],$H13)/SUMIFS(tblData[Total loans],tblData[State code],$I$7,tblData[Year],$H13) -> 346832.28 | M13: =SUMIFS(tblData[Q4 HPI YoY change],tblData[State code],$I$7,tblData[Year],$H13) -> 0.13443 | N13: 0.17312936 | P13: 2017 Q4 | Q13: 244.09 | R13: =INDEX($S$13:$BQ$13,MATCH($I$7,$S$1:$BQ$1,0)) -> 242.07 | S13: 207.59 | T13: 251.15 | U13: 293.03 | V13: 210.24 | W13: 265.39 | X13: 421.59 | Y13: 166.34 | Z13: 194.48 | AA13: 499.69 | AB13: 283.85 | AC13: 220.71 | AD13: 246.64 | AE13: 295.92 | AF13: 192.92 | AG13: 195.31 | AH13: 234.32 | AI13: 229.43 | AJ13: 226.2 | AK13: 270.31 | AL13: 234.03 | AM13: 240.54 | AN13: 268.79 | AO13: 209.67 | AP13: 267.75 | AQ13: 194.08 | AR13: 221.14 | AS13: 372.44 | AT13: 249.18 | AU13: 236.98 | AV13: 237.69 | AW13: 225.07 | AX13: 233.34 | AY13: 228.11 | AZ13: 223.83 | BA13: 302.13 | BB13: 186.98 | BC13: 228.8 | BD13: 395.83 | BE13: 212.32 | BF13: 216.25 | BG13: 226.27 | BH13: 280.08 | BI13: 244.55 | BJ13: 271.17 | BK13: 374.21 | BL13: 228.2 | BM13: 242.07 | BN13: 333 | BO13: 204.91 | BP13: 240.91 | BQ13: 326
A14: ID | B14: Idaho | C14: West | D14: 0.034792438 | E14: 0.74221927 | F14: 655.51 | H14: 2022 | I14: =SUMIFS(tblData[Purchase loans],tblData[State code],$I$7,tblData[Year],$H14) -> 130317 | J14: =SUMIFS(tblData[Refinance loans],tblData[State code],$I$7,tblData[Year],$H14) -> 27413 | K14: =SUMIFS(tblData[Cash-out refi loans],tblData[State code],$I$7,tblData[Year],$H14) -> 41261 | L14: =SUMIFS(tblData[Total dollar volume],tblData[State code],$I$7,tblData[Year],$H14)/SUMIFS(tblData[Total loans],tblData[State code],$I$7,tblData[Year],$H14) -> 375552.39 | M14: =SUMIFS(tblData[Q4 HPI YoY change],tblData[State code],$I$7,tblData[Year],$H14) -> 0.082709 | N14: 0.076199116 | P14: 2018 Q1 | Q14: 248.57 | R14: =INDEX($S$14:$BQ$14,MATCH($I$7,$S$1:$BQ$1,0)) -> 247.09 | S14: 209.46 | T14: 254.86 | U14: 301.55 | V14: 211.34 | W14: 270.78 | X14: 434.58 | Y14: 167.4 | Z14: 203.7 | AA14: 510.69 | AB14: 289.55 | AC14: 226.19 | AD14: 241.5 | AE14: 303.2 | AF14: 194.88 | AG14: 199.1 | AH14: 236.78 | AI14: 234.12 | AJ14: 229.55 | AK14: 272.06 | AL14: 238.85 | AM14: 242.38 | AN14: 272.94 | AO14: 214.51 | AP14: 273.12 | AQ14: 200.5 | AR14: 226.14 | AS14: 378.98 | AT14: 253.7 | AU14: 242.67 | AV14: 240.1 | AW14: 229.68 | AX14: 233.76 | AY14: 232.56 | AZ14: 228.12 | BA14: 304.93 | BB14: 190.44 | BC14: 228.49 | BD14: 407.16 | BE14: 215.47 | BF14: 221.31 | BG14: 230.12 | BH14: 285.6 | BI14: 248.15 | BJ14: 275.5 | BK14: 384.56 | BL14: 224.29 | BM14: 247.09 | BN14: 343.1 | BO14: 206.65 | BP14: 246.98 | BQ14: 329.44
A15: IL | B15: Illinois | C15: Midwest | D15: 0.055424601 | E15: 0.64443789 | F15: 334.38 | H15: 2023 | I15: =SUMIFS(tblData[Purchase loans],tblData[State code],$I$7,tblData[Year],$H15) -> 97993 | J15: =SUMIFS(tblData[Refinance loans],tblData[State code],$I$7,tblData[Year],$H15) -> 10567 | K15: =SUMIFS(tblData[Cash-out refi loans],tblData[State code],$I$7,tblData[Year],$H15) -> 17941 | L15: =SUMIFS(tblData[Total dollar volume],tblData[State code],$I$7,tblData[Year],$H15)/SUMIFS(tblData[Total loans],tblData[State code],$I$7,tblData[Year],$H15) -> 380744.38 | M15: =SUMIFS(tblData[Q4 HPI YoY change],tblData[State code],$I$7,tblData[Year],$H15) -> 0.071558 | N15: 0.06126857 | P15: 2018 Q2 | Q15: 251.42 | R15: =INDEX($S$15:$BQ$15,MATCH($I$7,$S$1:$BQ$1,0)) -> 247.58 | S15: 212.97 | T15: 253.45 | U15: 305.56 | V15: 213.02 | W15: 272.88 | X15: 439.46 | Y15: 167.79 | Z15: 202.88 | AA15: 516.88 | AB15: 295.29 | AC15: 230.32 | AD15: 246.53 | AE15: 313.81 | AF15: 195.82 | AG15: 202.4 | AH15: 240.62 | AI15: 236.17 | AJ15: 230.64 | AK15: 271.96 | AL15: 243.09 | AM15: 242.68 | AN15: 277.02 | AO15: 217.52 | AP15: 276.41 | AQ15: 202.42 | AR15: 227.65 | AS15: 381.77 | AT15: 255.44 | AU15: 252.63 | AV15: 242.74 | AW15: 230.19 | AX15: 235.94 | AY15: 234.37 | AZ15: 231.52 | BA15: 306.44 | BB15: 192.36 | BC15: 231.66 | BD15: 410.79 | BE15: 217.32 | BF15: 225.68 | BG15: 234.27 | BH15: 288.47 | BI15: 251.52 | BJ15: 278.5 | BK15: 393.82 | BL15: 226.4 | BM15: 247.58 | BN15: 349.5 | BO15: 207.9 | BP15: 251.07 | BQ15: 332.11
A16: IN | B16: Indiana | C16: Midwest | D16: 0.0345242 | E16: 0.67895635 | F16: 373.87 | H16: 2024 | I16: =SUMIFS(tblData[Purchase loans],tblData[State code],$I$7,tblData[Year],$H16) -> 102212 | J16: =SUMIFS(tblData[Refinance loans],tblData[State code],$I$7,tblData[Year],$H16) -> 20878 | K16: =SUMIFS(tblData[Cash-out refi loans],tblData[State code],$I$7,tblData[Year],$H16) -> 22530 | L16: =SUMIFS(tblData[Total dollar volume],tblData[State code],$I$7,tblData[Year],$H16)/SUMIFS(tblData[Total loans],tblData[State code],$I$7,tblData[Year],$H16) -> 407876.8 | M16: =SUMIFS(tblData[Q4 HPI YoY change],tblData[State code],$I$7,tblData[Year],$H16) -> 0.058691 | N16: 0.046090841 | P16: 2018 Q3 | Q16: 254.62 | R16: =INDEX($S$16:$BQ$16,MATCH($I$7,$S$1:$BQ$1,0)) -> 250.35 | S16: 215.26 | T16: 253.54 | U16: 310.53 | V16: 214.49 | W16: 276.36 | X16: 445.57 | Y16: 169.15 | Z16: 202.25 | AA16: 499.42 | AB16: 299.94 | AC16: 234.96 | AD16: 249.17 | AE16: 324.74 | AF16: 196.85 | AG16: 205.02 | AH16: 242.23 | AI16: 237.21 | AJ16: 233.1 | AK16: 273.08 | AL16: 246.17 | AM16: 244.03 | AN16: 279.81 | AO16: 220.77 | AP16: 280.4 | AQ16: 202.36 | AR16: 231.64 | AS16: 389.44 | AT16: 259.14 | AU16: 257.41 | AV16: 246.49 | AW16: 231.55 | AX16: 239.59 | AY16: 237.52 | AZ16: 234.96 | BA16: 306.47 | BB16: 195.56 | BC16: 233.94 | BD16: 415.71 | BE16: 219.34 | BF16: 229.22 | BG16: 237.27 | BH16: 295.17 | BI16: 257.03 | BJ16: 281.67 | BK16: 400.62 | BL16: 229.26 | BM16: 250.35 | BN16: 355.49 | BO16: 209.37 | BP16: 254.64 | BQ16: 334.45
A17: IA | B17: Iowa | C17: Midwest | D17: 0.022526572 | E17: 0.51051671 | F17: 380.62 | H17: 2025 | I17: =SUMIFS(tblData[Purchase loans],tblData[State code],$I$7,tblData[Year],$H17) -> 103337 | J17: =SUMIFS(tblData[Refinance loans],tblData[State code],$I$7,tblData[Year],$H17) -> 31796 | K17: =SUMIFS(tblData[Cash-out refi loans],tblData[State code],$I$7,tblData[Year],$H17) -> 28965 | L17: =SUMIFS(tblData[Total dollar volume],tblData[State code],$I$7,tblData[Year],$H17)/SUMIFS(tblData[Total loans],tblData[State code],$I$7,tblData[Year],$H17) -> 437686.75 | M17: =SUMIFS(tblData[Q4 HPI YoY change],tblData[State code],$I$7,tblData[Year],$H17) -> 0.037856 | N17: 0.020926756 | P17: 2018 Q4 | Q17: 257.39 | R17: =INDEX($S$17:$BQ$17,MATCH($I$7,$S$1:$BQ$1,0)) -> 252.98 | S17: 217.31 | T17: 254.71 | U17: 317.63 | V17: 217.09 | W17: 278.31 | X17: 450.3 | Y17: 170.18 | Z17: 201.98 | AA17: 529.7 | AB17: 303.71 | AC17: 237.13 | AD17: 252.83 | AE17: 332.35 | AF17: 197.34 | AG17: 207.79 | AH17: 244.43 | AI17: 241.9 | AJ17: 237.47 | AK17: 275.6 | AL17: 250.39 | AM17: 244.22 | AN17: 282.49 | AO17: 223.98 | AP17: 282.55 | AQ17: 205.46 | AR17: 234.63 | AS17: 389.51 | AT17: 262.49 | AU17: 260.99 | AV17: 251.01 | AW17: 232.89 | AX17: 243.06 | AY17: 238.66 | AZ17: 237.98 | BA17: 309.43 | BB17: 197.96 | BC17: 237.24 | BD17: 419.78 | BE17: 222 | BF17: 228.77 | BG17: 240.89 | BH17: 298.24 | BI17: 261.3 | BJ17: 285.03 | BK17: 409.87 | BL17: 233.66 | BM17: 252.98 | BN17: 358.86 | BO17: 205.22 | BP17: 257.95 | BQ17: 337.66
A18: KS | B18: Kansas | C18: Midwest | D18: 0.032146365 | E18: 0.63075897 | F18: 415.55 | H18: Chart titles | P18: 2019 Q1 | Q18: 260.51 | R18: =INDEX($S$18:$BQ$18,MATCH($I$7,$S$1:$BQ$1,0)) -> 255.15 | S18: 221.82 | T18: 258.59 | U18: 320.13 | V18: 220.64 | W18: 279.6 | X18: 454.19 | Y18: 170.84 | Z18: 199.66 | AA18: 509.57 | AB18: 308.49 | AC18: 240.18 | AD18: 254.31 | AE18: 344.47 | AF18: 199.05 | AG18: 212.36 | AH18: 246.38 | AI18: 244.68 | AJ18: 238.69 | AK18: 277.37 | AL18: 255.04 | AM18: 244.93 | AN18: 286.58 | AO18: 226.98 | AP18: 288.74 | AQ18: 207.02 | AR18: 237.05 | AS18: 392.06 | AT18: 264.64 | AU18: 266.72 | AV18: 252.94 | AW18: 235.04 | AX18: 245.4 | AY18: 240.2 | AZ18: 241.69 | BA18: 315.85 | BB18: 200.97 | BC18: 240.89 | BD18: 423.57 | BE18: 225.94 | BF18: 232.01 | BG18: 244.65 | BH18: 299.28 | BI18: 265.36 | BJ18: 288.06 | BK18: 416.32 | BL18: 236.5 | BM18: 255.15 | BN18: 364.6 | BO18: 214.59 | BP18: 261.4 | BQ18: 340.29
A19: KY | B19: Kentucky | C19: South | D19: 0.042576254 | E19: 0.65526156 | F19: 409.76 | H19: ="Loans originated by purpose, 2018-2025: "&$I$6 -> Loans originated by purpose, 2018-2025: Virginia | P19: 2019 Q2 | Q19: 263.54 | R19: =INDEX($S$19:$BQ$19,MATCH($I$7,$S$1:$BQ$1,0)) -> 258.98 | S19: 223.98 | T19: 263.22 | U19: 326.6 | V19: 222.72 | W19: 283.37 | X19: 462.64 | Y19: 172.02 | Z19: 209.13 | AA19: 519.52 | AB19: 311.28 | AC19: 244.2 | AD19: 253.44 | AE19: 350.91 | AF19: 200.58 | AG19: 214.85 | AH19: 246.43 | AI19: 246.45 | AJ19: 243.59 | AK19: 278.98 | AL19: 257.51 | AM19: 247.68 | AN19: 287.72 | AO19: 230.03 | AP19: 289.78 | AQ19: 208.15 | AR19: 239.36 | AS19: 405.74 | AT19: 268.77 | AU19: 268.65 | AV19: 257.76 | AW19: 236.24 | AX19: 249.07 | AY19: 243.4 | AZ19: 245.57 | BA19: 318.52 | BB19: 203.9 | BC19: 240.29 | BD19: 427.64 | BE19: 227.5 | BF19: 235.5 | BG19: 248.33 | BH19: 305.38 | BI19: 269.9 | BJ19: 290.92 | BK19: 423.8 | BL19: 238.68 | BM19: 258.98 | BN19: 368.83 | BO19: 214.45 | BP19: 264.79 | BQ19: 350.83
A20: LA | B20: Louisiana | C20: South | D20: 0.015855256 | E20: 0.29628846 | F20: 367.42 | H20: ="Q4 home price change, year over year: "&$I$6&" vs. U.S." -> Q4 home price change, year over year: Virginia vs. U.S. | P20: 2019 Q3 | Q20: 267 | R20: =INDEX($S$20:$BQ$20,MATCH($I$7,$S$1:$BQ$1,0)) -> 262.66 | S20: 227.71 | T20: 263.77 | U20: 333.95 | V20: 224.26 | W20: 287.22 | X20: 469.81 | Y20: 173.22 | Z20: 212.5 | AA20: 527.79 | AB20: 315.67 | AC20: 247.34 | AD20: 255.34 | AE20: 361.01 | AF20: 201.15 | AG20: 219.6 | AH20: 250.18 | AI20: 250.92 | AJ20: 244.93 | AK20: 280.7 | AL20: 262.94 | AM20: 250.24 | AN20: 291.97 | AO20: 232.87 | AP20: 293.81 | AQ20: 210.57 | AR20: 242.69 | AS20: 407.8 | AT20: 273.09 | AU20: 270.07 | AV20: 261.49 | AW20: 239.45 | AX20: 253.76 | AY20: 245.85 | AZ20: 248.66 | BA20: 316.16 | BB20: 206.71 | BC20: 244.8 | BD20: 434.49 | BE20: 229.8 | BF20: 238.34 | BG20: 250.3 | BH20: 304.01 | BI20: 273.72 | BJ20: 294.08 | BK20: 433.5 | BL20: 241.56 | BM20: 262.66 | BN20: 377.22 | BO20: 215.83 | BP20: 270.32 | BQ20: 352.96
A21: ME | B21: Maine | C21: Northeast | D21: 0.0097531364 | E21: 0.85635587 | F21: 495.35 | H21: ="House price index (1991 Q1 = 100), 2015 Q1-2026 Q2: "&$I$6&" vs. U.S." -> House price index (1991 Q1 = 100), 2015 Q1-2026 Q2: Virginia vs. U.S. | P21: 2019 Q4 | Q21: 271.47 | R21: =INDEX($S$21:$BQ$21,MATCH($I$7,$S$1:$BQ$1,0)) -> 266.58 | S21: 231.63 | T21: 265.43 | U21: 343.02 | V21: 225.52 | W21: 290.89 | X21: 477.8 | Y21: 174.33 | Z21: 216.19 | AA21: 556.61 | AB21: 322.6 | AC21: 252.72 | AD21: 262.53 | AE21: 376.25 | AF21: 203.34 | AG21: 222.68 | AH21: 251.98 | AI21: 254.82 | AJ21: 247.55 | AK21: 283.44 | AL21: 266.84 | AM21: 252.33 | AN21: 297.64 | AO21: 236.74 | AP21: 298.69 | AQ21: 212.19 | AR21: 249.03 | AS21: 416.37 | AT21: 274.14 | AU21: 272.88 | AV21: 265.11 | AW21: 243.63 | AX21: 256.58 | AY21: 250.44 | AZ21: 253.93 | BA21: 315.66 | BB21: 210.76 | BC21: 247.21 | BD21: 443.72 | BE21: 233.16 | BF21: 243.7 | BG21: 254.73 | BH21: 309.89 | BI21: 279.06 | BJ21: 298.66 | BK21: 442.82 | BL21: 243.24 | BM21: 266.58 | BN21: 387.09 | BO21: 220.87 | BP21: 274.89 | BQ21: 358.25
A22: MD | B22: Maryland | C22: South | D22: 0.009498256 | E22: 0.46189514 | F22: 368.88 | P22: 2020 Q1 | Q22: 276.66 | R22: =INDEX($S$22:$BQ$22,MATCH($I$7,$S$1:$BQ$1,0)) -> 272.54 | S22: 237.47 | T22: 267.5 | U22: 351.09 | V22: 228.51 | W22: 296.16 | X22: 485.98 | Y22: 176.81 | Z22: 216.11 | AA22: 551.9 | AB22: 330.45 | AC22: 258.7 | AD22: 268.76 | AE22: 388.75 | AF22: 205.49 | AG22: 228.58 | AH22: 255.19 | AI22: 257.47 | AJ22: 253.12 | AK22: 286.01 | AL22: 273.76 | AM22: 254.43 | AN22: 302.91 | AO22: 241.43 | AP22: 302.9 | AQ22: 215.07 | AR22: 252.56 | AS22: 437.48 | AT22: 281.51 | AU22: 278.61 | AV22: 271.62 | AW22: 249.2 | AX22: 263.92 | AY22: 254.58 | AZ22: 259.61 | BA22: 319.91 | BB22: 214.74 | BC22: 252.77 | BD22: 451.61 | BE22: 237.88 | BF22: 248.61 | BG22: 259.93 | BH22: 313.15 | BI22: 285.96 | BJ22: 303.15 | BK22: 456.7 | BL22: 256.38 | BM22: 272.54 | BN22: 397.38 | BO22: 216.53 | BP22: 279.49 | BQ22: 368.78
A23: MA | B23: Massachusetts | C23: Northeast | D23: 0.036297526 | E23: 0.62132106 | F23: 482.57 | P23: 2020 Q2 | Q23: 278.3 | R23: =INDEX($S$23:$BQ$23,MATCH($I$7,$S$1:$BQ$1,0)) -> 270.65 | S23: 239.03 | T23: 272 | U23: 357.47 | V23: 233.66 | W23: 296.78 | X23: 486.21 | Y23: 178.13 | Z23: 218.91 | AA23: 540.21 | AB23: 333.85 | AC23: 260.82 | AD23: 271.15 | AE23: 389.74 | AF23: 205.48 | AG23: 231.26 | AH23: 257.46 | AI23: 260.69 | AJ23: 255.33 | AK23: 290.01 | AL23: 275.93 | AM23: 256.58 | AN23: 301.27 | AO23: 241.74 | AP23: 305.23 | AQ23: 219.36 | AR23: 254.78 | AS23: 426.69 | AT23: 283.69 | AU23: 280.57 | AV23: 272.22 | AW23: 247.5 | AX23: 267.3 | AY23: 255.77 | AZ23: 260.97 | BA23: 321.21 | BB23: 218.21 | BC23: 257.25 | BD23: 451.3 | BE23: 238.78 | BF23: 245.64 | BG23: 263.16 | BH23: 318.68 | BI23: 289.3 | BJ23: 304.27 | BK23: 459.05 | BL23: 244.76 | BM23: 270.65 | BN23: 399.97 | BO23: 217.58 | BP23: 280.04 | BQ23: 367.94
A24: MI | B24: Michigan | C24: Midwest | D24: 0.036843332 | E24: 0.65954211 | F24: 392.88 | P24: 2020 Q3 | Q24: 288.78 | R24: =INDEX($S$24:$BQ$24,MATCH($I$7,$S$1:$BQ$1,0)) -> 283.02 | S24: 246.19 | T24: 273.46 | U24: 372.03 | V24: 240.08 | W24: 309.04 | X24: 506.76 | Y24: 187.35 | Z24: 225.97 | AA24: 570.16 | AB24: 343.4 | AC24: 269.86 | AD24: 269.81 | AE24: 418.4 | AF24: 212.64 | AG24: 239.34 | AH24: 263.44 | AI24: 272.74 | AJ24: 264.65 | AK24: 294.56 | AL24: 285.94 | AM24: 268.43 | AN24: 316.26 | AO24: 252.6 | AP24: 314.67 | AQ24: 224.25 | AR24: 265.75 | AS24: 452.15 | AT24: 294.27 | AU24: 289.61 | AV24: 288.03 | AW24: 260.28 | AX24: 276.27 | AY24: 263.76 | AZ24: 270.48 | BA24: 328.53 | BB24: 227.25 | BC24: 261.46 | BD24: 473.34 | BE24: 249.04 | BF24: 260.01 | BG24: 272.51 | BH24: 327.96 | BI24: 300.76 | BJ24: 314 | BK24: 480.83 | BL24: 257.42 | BM24: 283.02 | BN24: 419.79 | BO24: 226.12 | BP24: 290.65 | BQ24: 374.22
A25: MN | B25: Minnesota | C25: Midwest | D25: 0.024238917 | E25: 0.45709599 | F25: 435.22 | P25: 2020 Q4 | Q25: 301.66 | R25: =INDEX($S$25:$BQ$25,MATCH($I$7,$S$1:$BQ$1,0)) -> 294.95 | S25: 257.94 | T25: 288.15 | U25: 392.01 | V25: 250.04 | W25: 324.95 | X25: 529.56 | Y25: 198.14 | Z25: 234.17 | AA25: 576.55 | AB25: 361.22 | AC25: 281.95 | AD25: 280.15 | AE25: 453.26 | AF25: 220.01 | AG25: 250.28 | AH25: 272.77 | AI25: 283.06 | AJ25: 275.42 | AK25: 301.27 | AL25: 304.68 | AM25: 278.5 | AN25: 331.32 | AO25: 263.39 | AP25: 327.45 | AQ25: 229.31 | AR25: 275.32 | AS25: 479.07 | AT25: 305.35 | AU25: 302.55 | AV25: 303.54 | AW25: 273.21 | AX25: 286.51 | AY25: 277.86 | AZ25: 284.64 | BA25: 337.31 | BB25: 236.64 | BC25: 270.27 | BD25: 496.33 | BE25: 258.65 | BF25: 277.43 | BG25: 281.37 | BH25: 340.7 | BI25: 313.86 | BJ25: 325.86 | BK25: 512.21 | BL25: 273.41 | BM25: 294.95 | BN25: 441.99 | BO25: 233.93 | BP25: 304.15 | BQ25: 387.84
A26: MS | B26: Mississippi | C26: South | D26: 0.0060255704 | E26: 0.54536029 | F26: 327.91 | P26: 2021 Q1 | Q26: 312.53 | R26: =INDEX($S$26:$BQ$26,MATCH($I$7,$S$1:$BQ$1,0)) -> 303.42 | S26: 264.46 | T26: 289.21 | U26: 414.46 | V26: 255.99 | W26: 338.13 | X26: 549.41 | Y26: 206.36 | Z26: 245.57 | AA26: 599.55 | AB26: 375.36 | AC26: 293.58 | AD26: 288.39 | AE26: 483.53 | AF26: 226.27 | AG26: 258.11 | AH26: 279.28 | AI26: 289.46 | AJ26: 281.63 | AK26: 309.06 | AL26: 316.49 | AM26: 287.29 | AN26: 343.85 | AO26: 272.94 | AP26: 336.42 | AQ26: 235.71 | AR26: 285.19 | AS26: 502.87 | AT26: 315.14 | AU26: 314.2 | AV26: 316.34 | AW26: 284.2 | AX26: 294.91 | AY26: 287.5 | AZ26: 295.45 | BA26: 341.72 | BB26: 244 | BC26: 279.18 | BD26: 516.96 | BE26: 265.91 | BF26: 286.03 | BG26: 291.8 | BH26: 357.08 | BI26: 327.99 | BJ26: 339.05 | BK26: 544.53 | BL26: 282.18 | BM26: 303.42 | BN26: 461.09 | BO26: 239.19 | BP26: 311.74 | BQ26: 399.31
A27: MO | B27: Missouri | C27: Midwest | D27: 0.037058238 | E27: 0.6437377 | F27: 409.34 | P27: 2021 Q2 | Q27: 326.58 | R27: =INDEX($S$27:$BQ$27,MATCH($I$7,$S$1:$BQ$1,0)) -> 314.18 | S27: 277.05 | T27: 296.97 | U27: 442.96 | V27: 268.49 | W27: 355.6 | X27: 581.51 | Y27: 213.38 | Z27: 253.15 | AA27: 618.56 | AB27: 398.23 | AC27: 305.75 | AD27: 305.06 | AE27: 525.95 | AF27: 232.28 | AG27: 268.14 | AH27: 287.9 | AI27: 303.08 | AJ27: 293.81 | AK27: 315.83 | AL27: 336.58 | AM27: 293.7 | AN27: 357.57 | AO27: 283.05 | AP27: 348.97 | AQ27: 243.38 | AR27: 296.27 | AS27: 527.86 | AT27: 327.2 | AU27: 335.18 | AV27: 332.38 | AW27: 294.14 | AX27: 305.04 | AY27: 297.7 | AZ27: 310.89 | BA27: 350.41 | BB27: 253.13 | BC27: 289.45 | BD27: 543.15 | BE27: 275.85 | BF27: 302.84 | BG27: 309.51 | BH27: 367.65 | BI27: 346.27 | BJ27: 355.09 | BK27: 584.39 | BL27: 297.64 | BM27: 314.18 | BN27: 485.48 | BO27: 247.05 | BP27: 324.73 | BQ27: 414.01
A28: MT | B28: Montana | C28: West | D28: 0.02591725 | E28: 0.78221294 | F28: 742.06 | P28: 2021 Q3 | Q28: 341.25 | R28: =INDEX($S$28:$BQ$28,MATCH($I$7,$S$1:$BQ$1,0)) -> 325.31 | S28: 289.82 | T28: 309.66 | U28: 474.05 | V28: 280.72 | W28: 372.99 | X28: 609.48 | Y28: 220.43 | Z28: 260.09 | AA28: 614.1 | AB28: 427 | AC28: 323.61 | AD28: 326.1 | AE28: 559.07 | AF28: 240.3 | AG28: 277.29 | AH28: 295.54 | AI28: 311.94 | AJ28: 306.77 | AK28: 325.49 | AL28: 353.63 | AM28: 301.93 | AN28: 370.32 | AO28: 293.55 | AP28: 358.04 | AQ28: 252.24 | AR28: 306.71 | AS28: 571.53 | AT28: 338.92 | AU28: 358.24 | AV28: 347.19 | AW28: 303.3 | AX28: 319.14 | AY28: 307.06 | AZ28: 329.95 | BA28: 361.95 | BB28: 261.05 | BC28: 303.6 | BD28: 564.66 | BE28: 284.8 | BF28: 313.5 | BG28: 322.47 | BH28: 388.16 | BI28: 366.99 | BJ28: 372.78 | BK28: 621.91 | BL28: 313.52 | BM28: 325.31 | BN28: 506.9 | BO28: 257.22 | BP28: 335.7 | BQ28: 433.57
A29: NE | B29: Nebraska | C29: Midwest | D29: 0.019604238 | E29: 0.5950974 | F29: 437.28 | P29: 2021 Q4 | Q29: 354.13 | R29: =INDEX($S$29:$BQ$29,MATCH($I$7,$S$1:$BQ$1,0)) -> 334.88 | S29: 301.82 | T29: 318.62 | U29: 499.04 | V29: 296.46 | W29: 387.45 | X29: 625.19 | Y29: 225.72 | Z29: 270.26 | AA29: 612.73 | AB29: 453.6 | AC29: 339.87 | AD29: 338.88 | AE29: 579.22 | AF29: 246.67 | AG29: 286.8 | AH29: 302.88 | AI29: 319.51 | AJ29: 314.09 | AK29: 332.22 | AL29: 366.68 | AM29: 308.79 | AN29: 380.29 | AO29: 303.12 | AP29: 367.78 | AQ29: 265.24 | AR29: 317.62 | AS29: 594.23 | AT29: 349.6 | AU29: 372.8 | AV29: 358.76 | AW29: 314.9 | AX29: 329.59 | AY29: 315.28 | AZ29: 344.68 | BA29: 371.39 | BB29: 268.77 | BC29: 313.51 | BD29: 582.44 | BE29: 292.71 | BF29: 321.55 | BG29: 340.42 | BH29: 401.75 | BI29: 386.92 | BJ29: 389.04 | BK29: 650.71 | BL29: 323.71 | BM29: 334.88 | BN29: 528.47 | BO29: 262.96 | BP29: 345.17 | BQ29: 453.05
A30: NV | B30: Nevada | C30: West | D30: 0.026669802 | E30: 0.5813178 | F30: 431.51 | P30: 2022 Q1 | Q30: 369.14 | R30: =INDEX($S$30:$BQ$30,MATCH($I$7,$S$1:$BQ$1,0)) -> 348.75 | S30: 313.27 | T30: 323.02 | U30: 524.63 | V30: 305.3 | W30: 402.69 | X30: 663.44 | Y30: 234.42 | Z30: 280.42 | AA30: 632.24 | AB30: 482.74 | AC30: 356.71 | AD30: 349.01 | AE30: 603.36 | AF30: 254.91 | AG30: 297.69 | AH30: 312.14 | AI30: 331.7 | AJ30: 326.56 | AK30: 342.68 | AL30: 382.7 | AM30: 321.91 | AN30: 393.63 | AO30: 314.97 | AP30: 377.58 | AQ30: 272.66 | AR30: 329.73 | AS30: 626.31 | AT30: 360.71 | AU30: 392.02 | AV30: 378.91 | AW30: 326.35 | AX30: 341.96 | AY30: 328.22 | AZ30: 364.5 | BA30: 381 | BB30: 280 | BC30: 323.06 | BD30: 607.81 | BE30: 302.99 | BF30: 335.1 | BG30: 355.46 | BH30: 418.63 | BI30: 407.69 | BJ30: 404.85 | BK30: 685.95 | BL30: 338.11 | BM30: 348.75 | BN30: 553.97 | BO30: 273.26 | BP30: 357.81 | BQ30: 463.97
A31: NH | B31: New Hampshire | C31: Northeast | D31: 0.031094163 | E31: 0.83161706 | F31: 485.58 | P31: 2022 Q2 | Q31: 380.82 | R31: =INDEX($S$31:$BQ$31,MATCH($I$7,$S$1:$BQ$1,0)) -> 356.95 | S31: 321.36 | T31: 332.36 | U31: 548.86 | V31: 315.55 | W31: 408.33 | X31: 677.23 | Y31: 241.39 | Z31: 292.66 | AA31: 639.61 | AB31: 509.6 | AC31: 373.09 | AD31: 359.81 | AE31: 621 | AF31: 260.25 | AG31: 306.98 | AH31: 323.8 | AI31: 341.21 | AJ31: 334.87 | AK31: 348.22 | AL31: 407.11 | AM31: 326.08 | AN31: 403.93 | AO31: 321.02 | AP31: 387.12 | AQ31: 280.74 | AR31: 339.66 | AS31: 651.44 | AT31: 370.03 | AU31: 405.1 | AV31: 386.68 | AW31: 335.93 | AX31: 356.98 | AY31: 339.62 | AZ31: 383.75 | BA31: 386.76 | BB31: 288.13 | BC31: 334.01 | BD31: 613.78 | BE31: 308.36 | BF31: 346.85 | BG31: 371.82 | BH31: 434.98 | BI31: 424.69 | BJ31: 423.51 | BK31: 702.24 | BL31: 348.67 | BM31: 356.95 | BN31: 563.48 | BO31: 281.16 | BP31: 368.96 | BQ31: 482.6
A32: NJ | B32: New Jersey | C32: Northeast | D32: 0.045301621 | E32: 0.81714075 | F32: 442.71 | P32: 2022 Q3 | Q32: 380.39 | R32: =INDEX($S$32:$BQ$32,MATCH($I$7,$S$1:$BQ$1,0)) -> 358.35 | S32: 327.41 | T32: 339.11 | U32: 536.3 | V32: 320.97 | W32: 398.4 | X32: 659.56 | Y32: 243.43 | Z32: 283.91 | AA32: 621.69 | AB32: 515.67 | AC32: 374.37 | AD32: 364.15 | AE32: 603.17 | AF32: 261.32 | AG32: 310.81 | AH32: 326.09 | AI32: 342.39 | AJ32: 334.55 | AK32: 349.81 | AL32: 404.74 | AM32: 324.77 | AN32: 399.11 | AO32: 320.65 | AP32: 383.74 | AQ32: 287.22 | AR32: 341.13 | AS32: 647.2 | AT32: 372.89 | AU32: 388.52 | AV32: 386.6 | AW32: 340.18 | AX32: 358.98 | AY32: 338.63 | AZ32: 384.54 | BA32: 391.53 | BB32: 288.38 | BC32: 336.47 | BD32: 605.8 | BE32: 310.38 | BF32: 346.12 | BG32: 379.64 | BH32: 440.63 | BI32: 428.17 | BJ32: 423.58 | BK32: 682.61 | BL32: 353.08 | BM32: 358.35 | BN32: 554.47 | BO32: 278.4 | BP32: 372.27 | BQ32: 486.5
A33: NM | B33: New Mexico | C33: West | D33: -0.011704131 | E33: 0.59236885 | F33: 408.57 | P33: 2022 Q4 | Q33: 381.31 | R33: =INDEX($S$33:$BQ$33,MATCH($I$7,$S$1:$BQ$1,0)) -> 362.94 | S33: 331.07 | T33: 336.43 | U33: 524.86 | V33: 324.22 | W33: 392.57 | X33: 654.81 | Y33: 245.7 | Z33: 303.01 | AA33: 587.39 | AB33: 512.78 | AC33: 377.66 | AD33: 393.1 | AE33: 593.5 | AF33: 263.7 | AG33: 312.23 | AH33: 328.34 | AI33: 346.14 | AJ33: 343.88 | AK33: 347.99 | AL33: 413.97 | AM33: 327.55 | AN33: 400.02 | AO33: 322.35 | AP33: 384.37 | AQ33: 285.36 | AR33: 344.21 | AS33: 655.78 | AT33: 378.88 | AU33: 383.59 | AV33: 392.63 | AW33: 340.93 | AX33: 361.9 | AY33: 339.59 | AZ33: 389.05 | BA33: 393.52 | BB33: 291.19 | BC33: 343.54 | BD33: 602.6 | BE33: 314.1 | BF33: 339.34 | BG33: 381.01 | BH33: 438.66 | BI33: 426.74 | BJ33: 424.24 | BK33: 671.79 | BL33: 355.05 | BM33: 362.94 | BN33: 545.41 | BO33: 278.66 | BP33: 378.55 | BQ33: 486.9
A34: NY | B34: New York | C34: Northeast | D34: 0.035499455 | E34: 0.71170739 | F34: 428.68 | P34: 2023 Q1 | Q34: 384.24 | R34: =INDEX($S$34:$BQ$34,MATCH($I$7,$S$1:$BQ$1,0)) -> 368.55 | S34: 336.37 | T34: 343.41 | U34: 526.66 | V34: 330.47 | W34: 390.63 | X34: 653.01 | Y34: 252.31 | Z34: 294.5 | AA34: 610.21 | AB34: 517.98 | AC34: 378.49 | AD34: 365.81 | AE34: 591.08 | AF34: 266.79 | AG34: 316.28 | AH34: 334.79 | AI34: 348.02 | AJ34: 350.67 | AK34: 346.19 | AL34: 416.21 | AM34: 328.43 | AN34: 405.03 | AO34: 327.59 | AP34: 387.65 | AQ34: 292.29 | AR34: 348.1 | AS34: 662.15 | AT34: 384.21 | AU34: 375.12 | AV34: 400.48 | AW34: 346.8 | AX34: 366.99 | AY34: 343 | AZ34: 393.28 | BA34: 397.66 | BB34: 296.65 | BC34: 345.73 | BD34: 595.31 | BE34: 317.3 | BF34: 360.19 | BG34: 388.01 | BH34: 452.06 | BI34: 433.58 | BJ34: 424.51 | BK34: 658.06 | BL34: 360.85 | BM34: 368.55 | BN34: 541.64 | BO34: 286.45 | BP34: 383.78 | BQ34: 492.66
A35: NC | B35: North Carolina | C35: South | D35: 0.003763974 | E35: 0.72905919 | F35: 439.06 | P35: 2023 Q2 | Q35: 391.53 | R35: =INDEX($S$35:$BQ$35,MATCH($I$7,$S$1:$BQ$1,0)) -> 374.55 | S35: 335.21 | T35: 345.92 | U35: 532.66 | V35: 333.71 | W35: 399.98 | X35: 661.8 | Y35: 260.15 | Z35: 300.73 | AA35: 604.97 | AB35: 525.2 | AC35: 389.42 | AD35: 382.36 | AE35: 598.52 | AF35: 273.58 | AG35: 324.46 | AH35: 337.03 | AI35: 357.95 | AJ35: 353.46 | AK35: 352.32 | AL35: 432.78 | AM35: 339.77 | AN35: 416.84 | AO35: 335.27 | AP35: 396.24 | AQ35: 294.85 | AR35: 357.27 | AS35: 674.38 | AT35: 389.62 | AU35: 382.77 | AV35: 411.79 | AW35: 358.96 | AX35: 370.36 | AY35: 352.78 | AZ35: 400.92 | BA35: 403.98 | BB35: 303.44 | BC35: 351.94 | BD35: 603.86 | BE35: 323.75 | BF35: 362.44 | BG35: 394.97 | BH35: 456.18 | BI35: 437.36 | BJ35: 427.98 | BK35: 668.88 | BL35: 373.41 | BM35: 374.55 | BN35: 545.37 | BO35: 287.02 | BP35: 393.47 | BQ35: 497.7
A36: ND | B36: North Dakota | C36: Midwest | D36: 0.04824042 | E36: 0.466673 | F36: 462.97 | P36: 2023 Q3 | Q36: 400 | R36: =INDEX($S$36:$BQ$36,MATCH($I$7,$S$1:$BQ$1,0)) -> 383.48 | S36: 345.4 | T36: 348.39 | U36: 545.4 | V36: 337.5 | W36: 407.27 | X36: 673.72 | Y36: 267.03 | Z36: 307.2 | AA36: 610.77 | AB36: 540.31 | AC36: 398.43 | AD36: 367.24 | AE36: 603.75 | AF36: 280.65 | AG36: 328.97 | AH36: 343.33 | AI36: 367.6 | AJ36: 358.88 | AK36: 354.92 | AL36: 448.95 | AM36: 345.37 | AN36: 426.83 | AO36: 344.37 | AP36: 399.33 | AQ36: 294.22 | AR36: 364.27 | AS36: 674.73 | AT36: 399 | AU36: 393 | AV36: 422.9 | AW36: 370.95 | AX36: 381.3 | AY36: 364.73 | AZ36: 411.97 | BA36: 401.49 | BB36: 310.4 | BC36: 357.51 | BD36: 611.86 | BE36: 331.85 | BF36: 376.09 | BG36: 404.59 | BH36: 461.4 | BI36: 444.56 | BJ36: 434.27 | BK36: 682.85 | BL36: 403.23 | BM36: 383.48 | BN36: 557.53 | BO36: 296.97 | BP36: 404.82 | BQ36: 505.35
A37: OH | B37: Ohio | C37: Midwest | D37: 0.043308322 | E37: 0.70397609 | F37: 359.13 | P37: 2023 Q4 | Q37: 404.65 | R37: =INDEX($S$37:$BQ$37,MATCH($I$7,$S$1:$BQ$1,0)) -> 389.05 | S37: 344.66 | T37: 358.43 | U37: 554.88 | V37: 342.47 | W37: 411.59 | X37: 674.57 | Y37: 273.6 | Z37: 316.61 | AA37: 599.19 | AB37: 544.51 | AC37: 401.99 | AD37: 379.99 | AE37: 606.23 | AF37: 286.1 | AG37: 334.74 | AH37: 347.35 | AI37: 373.23 | AJ37: 364.01 | AK37: 354.12 | AL37: 440.87 | AM37: 344.94 | AN37: 435.23 | AO37: 350.6 | AP37: 400.54 | AQ37: 315.6 | AR37: 368.74 | AS37: 682.14 | AT37: 396.63 | AU37: 396.78 | AV37: 428.66 | AW37: 379.49 | AX37: 381.01 | AY37: 371.32 | AZ37: 412.41 | BA37: 414.14 | BB37: 316.23 | BC37: 357.85 | BD37: 608.48 | BE37: 336.1 | BF37: 386.07 | BG37: 413.87 | BH37: 467.14 | BI37: 453.52 | BJ37: 434.58 | BK37: 685.25 | BL37: 393.57 | BM37: 389.05 | BN37: 564.06 | BO37: 313.23 | BP37: 411.52 | BQ37: 500.17
A38: OK | B38: Oklahoma | C38: South | D38: 0.019232287 | E38: 0.54714615 | F38: 382.47 | P38: 2024 Q1 | Q38: 408.9 | R38: =INDEX($S$38:$BQ$38,MATCH($I$7,$S$1:$BQ$1,0)) -> 392.23 | S38: 347.6 | T38: 356.39 | U38: 553.05 | V38: 347.61 | W38: 414.19 | X38: 676.51 | Y38: 275.88 | Z38: 327.03 | AA38: 595.99 | AB38: 546.8 | AC38: 406.24 | AD38: 401.63 | AE38: 614.89 | AF38: 291.88 | AG38: 340.41 | AH38: 352.77 | AI38: 381.13 | AJ38: 369.26 | AK38: 353.32 | AL38: 456.68 | AM38: 349.49 | AN38: 440.45 | AO38: 354.23 | AP38: 406.24 | AQ38: 298.01 | AR38: 375.71 | AS38: 693.37 | AT38: 408.92 | AU38: 407.15 | AV38: 438.73 | AW38: 388.48 | AX38: 389.21 | AY38: 379.46 | AZ38: 418.69 | BA38: 413.59 | BB38: 319.41 | BC38: 363.02 | BD38: 617.57 | BE38: 340.06 | BF38: 385.94 | BG38: 420.77 | BH38: 468.68 | BI38: 457.33 | BJ38: 437.36 | BK38: 691.79 | BL38: 407.49 | BM38: 392.23 | BN38: 565.92 | BO38: 295.49 | BP38: 420.45 | BQ38: 519.23
A39: OR | B39: Oregon | C39: West | D39: 0.002396016 | E39: 0.41794375 | F39: 629.17 | P39: 2024 Q2 | Q39: 413.84 | R39: =INDEX($S$39:$BQ$39,MATCH($I$7,$S$1:$BQ$1,0)) -> 402.12 | S39: 353.44 | T39: 364.22 | U39: 562.26 | V39: 351.62 | W39: 416.5 | X39: 681.26 | Y39: 283.18 | Z39: 328.95 | AA39: 624.47 | AB39: 549.83 | AC39: 412.22 | AD39: 390.02 | AE39: 606.23 | AF39: 295.61 | AG39: 344.9 | AH39: 356.36 | AI39: 383.07 | AJ39: 376.28 | AK39: 357.47 | AL39: 462.42 | AM39: 353.45 | AN39: 444.66 | AO39: 361.81 | AP39: 409.35 | AQ39: 304.43 | AR39: 380.67 | AS39: 703.68 | AT39: 415.15 | AU39: 409.85 | AV39: 443.33 | AW39: 393.6 | AX39: 392.57 | AY39: 384.63 | AZ39: 423.92 | BA39: 416.45 | BB39: 326.14 | BC39: 366.42 | BD39: 618.9 | BE39: 347.07 | BF39: 397.47 | BG39: 423.3 | BH39: 475.11 | BI39: 460.89 | BJ39: 439.95 | BK39: 698.25 | BL39: 418.47 | BM39: 402.12 | BN39: 571.98 | BO39: 318.57 | BP39: 425.6 | BQ39: 521.79
A40: PA | B40: Pennsylvania | C40: Northeast | D40: 0.038893387 | E40: 0.62347744 | F40: 378.53 | P40: 2024 Q3 | Q40: 417.79 | R40: =INDEX($S$40:$BQ$40,MATCH($I$7,$S$1:$BQ$1,0)) -> 406.94 | S40: 356.9 | T40: 372.68 | U40: 563.03 | V40: 356.55 | W40: 420.02 | X40: 684.7 | Y40: 289.99 | Z40: 331.08 | AA40: 603.7 | AB40: 548.34 | AC40: 415.33 | AD40: 407.71 | AE40: 626.94 | AF40: 300.3 | AG40: 351.29 | AH40: 359.17 | AI40: 388.03 | AJ40: 381.52 | AK40: 351.46 | AL40: 466.4 | AM40: 358.88 | AN40: 452.55 | AO40: 367.61 | AP40: 414.65 | AQ40: 310.03 | AR40: 385.32 | AS40: 717.57 | AT40: 413.54 | AU40: 409.1 | AV40: 454.51 | AW40: 401.58 | AX40: 396.15 | AY40: 390.11 | AZ40: 427.47 | BA40: 420.52 | BB40: 332.14 | BC40: 368.33 | BD40: 624.32 | BE40: 351.09 | BF40: 406.64 | BG40: 425.57 | BH40: 477.3 | BI40: 467.47 | BJ40: 440.78 | BK40: 706.69 | BL40: 420.25 | BM40: 406.94 | BN40: 576.17 | BO40: 311.8 | BP40: 431.83 | BQ40: 531.29
A41: RI | B41: Rhode Island | C41: Northeast | D41: 0.045936974 | E41: 0.80783751 | F41: 440.57 | P41: 2024 Q4 | Q41: 423.13 | R41: =INDEX($S$41:$BQ$41,MATCH($I$7,$S$1:$BQ$1,0)) -> 411.87 | S41: 361.23 | T41: 372.19 | U41: 564.31 | V41: 357.39 | W41: 421.65 | X41: 689.32 | Y41: 297.64 | Z41: 327.21 | AA41: 616.95 | AB41: 555.38 | AC41: 421.33 | AD41: 392.44 | AE41: 640.1 | AF41: 307.1 | AG41: 356.41 | AH41: 364.86 | AI41: 394.11 | AJ41: 387.9 | AK41: 356.07 | AL41: 474.83 | AM41: 364.96 | AN41: 459.23 | AO41: 368.01 | AP41: 418.84 | AQ41: 313.75 | AR41: 388.28 | AS41: 734.69 | AT41: 425.03 | AU41: 420.84 | AV41: 460.78 | AW41: 412.22 | AX41: 403.88 | AY41: 399.07 | AZ41: 434.63 | BA41: 426.42 | BB41: 337.38 | BC41: 372.84 | BD41: 627.35 | BE41: 357.03 | BF41: 412.26 | BG41: 435.49 | BH41: 484.61 | BI41: 473.79 | BJ41: 444.42 | BK41: 716.68 | BL41: 420.94 | BM41: 411.87 | BN41: 580.55 | BO41: 324.03 | BP41: 439.32 | BQ41: 537.76
A42: SC | B42: South Carolina | C42: South | D42: 0.023222192 | E42: 0.76653712 | F42: 449.99 | P42: 2025 Q1 | Q42: 426.19 | R42: =INDEX($S$42:$BQ$42,MATCH($I$7,$S$1:$BQ$1,0)) -> 419.57 | S42: 363.65 | T42: 378.58 | U42: 565.66 | V42: 359.04 | W42: 421.57 | X42: 690.02 | Y42: 301.93 | Z42: 334.55 | AA42: 613.74 | AB42: 548.36 | AC42: 423.14 | AD42: 394.03 | AE42: 632.04 | AF42: 310.06 | AG42: 358.27 | AH42: 366.09 | AI42: 400.66 | AJ42: 388.02 | AK42: 361.14 | AL42: 488.11 | AM42: 365.6 | AN42: 464.13 | AO42: 378.61 | AP42: 421.8 | AQ42: 317.07 | AR42: 392.12 | AS42: 730.71 | AT42: 423.41 | AU42: 422.98 | AV42: 463.93 | AW42: 418.6 | AX42: 407.75 | AY42: 405.49 | AZ42: 436.94 | BA42: 430.56 | BB42: 343.68 | BC42: 380.01 | BD42: 626.68 | BE42: 362.87 | BF42: 430.41 | BG42: 437.87 | BH42: 485.31 | BI42: 470.47 | BJ42: 446.73 | BK42: 719.48 | BL42: 425.26 | BM42: 419.57 | BN42: 587.21 | BO42: 322.58 | BP42: 447.68 | BQ42: 543.1
A43: SD | B43: South Dakota | C43: Midwest | D43: 0.011451072 | E43: 0.60485979 | F43: 497.33 | P43: 2025 Q2 | Q43: 426.58 | R43: =INDEX($S$43:$BQ$43,MATCH($I$7,$S$1:$BQ$1,0)) -> 418.39 | S43: 365.61 | T43: 376.58 | U43: 561.31 | V43: 366.06 | W43: 418 | X43: 677.91 | Y43: 304.82 | Z43: 336.48 | AA43: 594.5 | AB43: 542.23 | AC43: 417.74 | AD43: 397.82 | AE43: 632.64 | AF43: 316.62 | AG43: 361.12 | AH43: 372.25 | AI43: 402.14 | AJ43: 393.05 | AK43: 361.51 | AL43: 489.9 | AM43: 365.11 | AN43: 465.62 | AO43: 378.5 | AP43: 424.55 | AQ43: 326.39 | AR43: 394.51 | AS43: 721.98 | AT43: 428.6 | AU43: 419.89 | AV43: 470.86 | AW43: 423.29 | AX43: 413.74 | AY43: 414.05 | AZ43: 437.25 | BA43: 441.75 | BB43: 343.94 | BC43: 375.02 | BD43: 627.35 | BE43: 364.21 | BF43: 420.98 | BG43: 439.55 | BH43: 491.84 | BI43: 475.22 | BJ43: 442.24 | BK43: 717.31 | BL43: 422.18 | BM43: 418.39 | BN43: 587.91 | BO43: 326.9 | BP43: 452.41 | BQ43: 546.42
A44: TN | B44: Tennessee | C44: South | D44: 0.0085073633 | E44: 0.71791013 | F44: 479.4 | P44: 2025 Q3 | Q44: 428.05 | R44: =INDEX($S$44:$BQ$44,MATCH($I$7,$S$1:$BQ$1,0)) -> 422.76 | S44: 364.35 | T44: 376.35 | U44: 561.23 | V44: 364.03 | W44: 417.74 | X44: 680.01 | Y44: 308.13 | Z44: 342.28 | AA44: 607.03 | AB44: 537.24 | AC44: 419.64 | AD44: 419.42 | AE44: 636.99 | AF44: 322.22 | AG44: 361.62 | AH44: 374.31 | AI44: 405.83 | AJ44: 396.9 | AK44: 363.32 | AL44: 491.09 | AM44: 366.3 | AN44: 467.85 | AO44: 382.24 | AP44: 428.44 | AQ44: 323.8 | AR44: 396.84 | AS44: 729.03 | AT44: 431 | AU44: 422.92 | AV44: 471.94 | AW44: 425.53 | AX44: 406.97 | AY44: 417.56 | AZ44: 436.72 | BA44: 447.4 | BB44: 349.05 | BC44: 377.01 | BD44: 626.39 | BE44: 367.82 | BF44: 423.08 | BG44: 443.24 | BH44: 491.57 | BI44: 474.73 | BJ44: 441.17 | BK44: 716.17 | BL44: 417.5 | BM44: 422.76 | BN44: 584.51 | BO44: 330.53 | BP44: 457.74 | BQ44: 540.94
A45: TX | B45: Texas | C45: South | D45: 0.0042776936 | E45: 0.4874774 | F45: 444.25 | P45: 2025 Q4 | Q45: 431.73 | R45: =INDEX($S$45:$BQ$45,MATCH($I$7,$S$1:$BQ$1,0)) -> 427.3 | S45: 370.1 | T45: 389.25 | U45: 568.11 | V45: 371.67 | W45: 419.4 | X45: 678.67 | Y45: 311.35 | Z45: 349.76 | AA45: 610.27 | AB45: 542.09 | AC45: 421.15 | AD45: 394.96 | AE45: 634.37 | AF45: 326.63 | AG45: 368.12 | AH45: 378.27 | AI45: 410.05 | AJ45: 398.91 | AK45: 368.23 | AL45: 493.92 | AM45: 368.95 | AN45: 470.6 | AO45: 389.15 | AP45: 432.3 | AQ45: 323.56 | AR45: 406.1 | AS45: 724.98 | AT45: 434.63 | AU45: 423.29 | AV45: 478.2 | AW45: 432.42 | AX45: 406.51 | AY45: 421.23 | AZ45: 439.06 | BA45: 453.12 | BB45: 352.92 | BC45: 385.27 | BD45: 629.83 | BE45: 371.89 | BF45: 431.47 | BG45: 444.03 | BH45: 495.06 | BI45: 475.69 | BJ45: 441.96 | BK45: 721.61 | BL45: 437.34 | BM45: 427.3 | BN45: 592.73 | BO45: 325.37 | BP45: 464.13 | BQ45: 555.35
A46: UT | B46: Utah | C46: West | D46: 0.009914956 | E46: 0.63700827 | F46: 724.9 | P46: 2026 Q1 | Q46: 434.18 | R46: =INDEX($S$46:$BQ$46,MATCH($I$7,$S$1:$BQ$1,0)) -> 429.82 | S46: 371.88 | T46: 403.1 | U46: 567.03 | V46: 370.01 | W46: 419.76 | X46: 674.2 | Y46: 316.3 | Z46: 341.08 | AA46: 604.03 | AB46: 546.49 | AC46: 425.06 | AD46: 402.04 | AE46: 650.76 | AF46: 332.69 | AG46: 372.78 | AH46: 379.52 | AI46: 412.76 | AJ46: 406.52 | AK46: 365.86 | AL46: 501.89 | AM46: 368.96 | AN46: 476.27 | AO46: 391.35 | AP46: 434.17 | AQ46: 329.39 | AR46: 407.68 | AS46: 729.12 | AT46: 439.55 | AU46: 424.57 | AV46: 480.5 | AW46: 438.19 | AX46: 415.71 | AY46: 425.37 | AZ46: 440.01 | BA46: 458.17 | BB46: 355.99 | BC46: 379.57 | BD46: 630.3 | BE46: 376.47 | BF46: 430.38 | BG46: 444.97 | BH46: 500.37 | BI46: 480.74 | BJ46: 441.23 | BK46: 724.5 | BL46: 446 | BM46: 429.82 | BN46: 585.64 | BO46: 338.69 | BP46: 468.94 | BQ46: 554.01
A47: VT | B47: Vermont | C47: Northeast | D47: 0.071611133 | E47: 0.86211149 | F47: 452.94 | P47: 2026 Q2 | Q47: 435.69 | R47: =INDEX($S$47:$BQ$47,MATCH($I$7,$S$1:$BQ$1,0)) -> 431.35 | S47: 375.76 | T47: 407.85 | U47: 564.57 | V47: 370.19 | W47: 417.15 | X47: 674.35 | Y47: 319.12 | Z47: 347.62 | AA47: 604.4 | AB47: 547.45 | AC47: 425.66 | AD47: 420.96 | AE47: 655.51 | AF47: 334.38 | AG47: 373.87 | AH47: 380.62 | AI47: 415.55 | AJ47: 409.76 | AK47: 367.42 | AL47: 495.35 | AM47: 368.88 | AN47: 482.57 | AO47: 392.88 | AP47: 435.22 | AQ47: 327.91 | AR47: 409.34 | AS47: 742.06 | AT47: 437.28 | AU47: 431.51 | AV47: 485.58 | AW47: 442.71 | AX47: 408.57 | AY47: 428.68 | AZ47: 439.06 | BA47: 462.97 | BB47: 359.13 | BC47: 382.47 | BD47: 629.17 | BE47: 378.53 | BF47: 440.57 | BG47: 449.99 | BH47: 497.33 | BI47: 479.4 | BJ47: 444.25 | BK47: 724.9 | BL47: 452.94 | BM47: 431.35 | BN47: 582.36 | BO47: 345.15 | BP47: 474.21 | BQ47: 564.09
A48: VA | B48: Virginia | C48: South | D48: 0.030320098 | E48: 0.61808838 | F48: 431.35
A49: WA | B49: Washington | C49: West | D49: -0.009997675 | E49: 0.50445633 | F49: 582.36
A50: WV | B50: West Virginia | C50: South | D50: 0.056915248 | E50: 0.56268393 | F50: 345.15
A51: WI | B51: Wisconsin | C51: Midwest | D51: 0.047646893 | E51: 0.72509004 | F51: 474.21
A52: WY | B52: Wyoming | C52: West | D52: 0.032051282 | E52: 0.57457083 | F52: 564.09
A55: Total loans by state and year (sparkline source)
A56: State | B56: 2018 | C56: 2019 | D56: 2020 | E56: 2021 | F56: 2022 | G56: 2023 | H56: 2024 | I56: 2025
A57: Alabama | B57: =SUMIFS(tblData[Total loans],tblData[State],$A57,tblData[Year],B$56) -> 93410 | C57: =SUMIFS(tblData[Total loans],tblData[State],$A57,tblData[Year],C$56) -> 109286 | D57: =SUMIFS(tblData[Total loans],tblData[State],$A57,tblData[Year],D$56) -> 173808 | E57: =SUMIFS(tblData[Total loans],tblData[State],$A57,tblData[Year],E$56) -> 184630 | F57: =SUMIFS(tblData[Total loans],tblData[State],$A57,tblData[Year],F$56) -> 111430 | G57: =SUMIFS(tblData[Total loans],tblData[State],$A57,tblData[Year],G$56) -> 79109 | H57: =SUMIFS(tblData[Total loans],tblData[State],$A57,tblData[Year],H$56) -> 87245 | I57: =SUMIFS(tblData[Total loans],tblData[State],$A57,tblData[Year],I$56) -> 96603
A58: Alaska | B58: =SUMIFS(tblData[Total loans],tblData[State],$A58,tblData[Year],B$56) -> 12307 | C58: =SUMIFS(tblData[Total loans],tblData[State],$A58,tblData[Year],C$56) -> 14447 | D58: =SUMIFS(tblData[Total loans],tblData[State],$A58,tblData[Year],D$56) -> 25287 | E58: =SUMIFS(tblData[Total loans],tblData[State],$A58,tblData[Year],E$56) -> 27032 | F58: =SUMIFS(tblData[Total loans],tblData[State],$A58,tblData[Year],F$56) -> 15717 | G58: =SUMIFS(tblData[Total loans],tblData[State],$A58,tblData[Year],G$56) -> 8342 | H58: =SUMIFS(tblData[Total loans],tblData[State],$A58,tblData[Year],H$56) -> 9248 | I58: =SUMIFS(tblData[Total loans],tblData[State],$A58,tblData[Year],I$56) -> 10371
A59: Arizona | B59: =SUMIFS(tblData[Total loans],tblData[State],$A59,tblData[Year],B$56) -> 195272 | C59: =SUMIFS(tblData[Total loans],tblData[State],$A59,tblData[Year],C$56) -> 272557 | D59: =SUMIFS(tblData[Total loans],tblData[State],$A59,tblData[Year],D$56) -> 467877 | E59: =SUMIFS(tblData[Total loans],tblData[State],$A59,tblData[Year],E$56) -> 460722 | F59: =SUMIFS(tblData[Total loans],tblData[State],$A59,tblData[Year],F$56) -> 206046 | G59: =SUMIFS(tblData[Total loans],tblData[State],$A59,tblData[Year],G$56) -> 118118 | H59: =SUMIFS(tblData[Total loans],tblData[State],$A59,tblData[Year],H$56) -> 133597 | I59: =SUMIFS(tblData[Total loans],tblData[State],$A59,tblData[Year],I$56) -> 150285
A60: Arkansas | B60: =SUMIFS(tblData[Total loans],tblData[State],$A60,tblData[Year],B$56) -> 56082 | C60: =SUMIFS(tblData[Total loans],tblData[State],$A60,tblData[Year],C$56) -> 62199 | D60: =SUMIFS(tblData[Total loans],tblData[State],$A60,tblData[Year],D$56) -> 97061 | E60: =SUMIFS(tblData[Total loans],tblData[State],$A60,tblData[Year],E$56) -> 101059 | F60: =SUMIFS(tblData[Total loans],tblData[State],$A60,tblData[Year],F$56) -> 62826 | G60: =SUMIFS(tblData[Total loans],tblData[State],$A60,tblData[Year],G$56) -> 45314 | H60: =SUMIFS(tblData[Total loans],tblData[State],$A60,tblData[Year],H$56) -> 48961 | I60: =SUMIFS(tblData[Total loans],tblData[State],$A60,tblData[Year],I$56) -> 56196
A61: California | B61: =SUMIFS(tblData[Total loans],tblData[State],$A61,tblData[Year],B$56) -> 724836 | C61: =SUMIFS(tblData[Total loans],tblData[State],$A61,tblData[Year],C$56) -> 1040660 | D61: =SUMIFS(tblData[Total loans],tblData[State],$A61,tblData[Year],D$56) -> 1892805 | E61: =SUMIFS(tblData[Total loans],tblData[State],$A61,tblData[Year],E$56) -> 1893079 | F61: =SUMIFS(tblData[Total loans],tblData[State],$A61,tblData[Year],F$56) -> 667679 | G61: =SUMIFS(tblData[Total loans],tblData[State],$A61,tblData[Year],G$56) -> 335898 | H61: =SUMIFS(tblData[Total loans],tblData[State],$A61,tblData[Year],H$56) -> 406064 | I61: =SUMIFS(tblData[Total loans],tblData[State],$A61,tblData[Year],I$56) -> 464185
A62: Colorado | B62: =SUMIFS(tblData[Total loans],tblData[State],$A62,tblData[Year],B$56) -> 191747 | C62: =SUMIFS(tblData[Total loans],tblData[State],$A62,tblData[Year],C$56) -> 268354 | D62: =SUMIFS(tblData[Total loans],tblData[State],$A62,tblData[Year],D$56) -> 450949 | E62: =SUMIFS(tblData[Total loans],tblData[State],$A62,tblData[Year],E$56) -> 407149 | F62: =SUMIFS(tblData[Total loans],tblData[State],$A62,tblData[Year],F$56) -> 172064 | G62: =SUMIFS(tblData[Total loans],tblData[State],$A62,tblData[Year],G$56) -> 102034 | H62: =SUMIFS(tblData[Total loans],tblData[State],$A62,tblData[Year],H$56) -> 113144 | I62: =SUMIFS(tblData[Total loans],tblData[State],$A62,tblData[Year],I$56) -> 129576
A63: Connecticut | B63: =SUMIFS(tblData[Total loans],tblData[State],$A63,tblData[Year],B$56) -> 62539 | C63: =SUMIFS(tblData[Total loans],tblData[State],$A63,tblData[Year],C$56) -> 72965 | D63: =SUMIFS(tblData[Total loans],tblData[State],$A63,tblData[Year],D$56) -> 125027 | E63: =SUMIFS(tblData[Total loans],tblData[State],$A63,tblData[Year],E$56) -> 143971 | F63: =SUMIFS(tblData[Total loans],tblData[State],$A63,tblData[Year],F$56) -> 72796 | G63: =SUMIFS(tblData[Total loans],tblData[State],$A63,tblData[Year],G$56) -> 47680 | H63: =SUMIFS(tblData[Total loans],tblData[State],$A63,tblData[Year],H$56) -> 50951 | I63: =SUMIFS(tblData[Total loans],tblData[State],$A63,tblData[Year],I$56) -> 57666
A64: Delaware | B64: =SUMIFS(tblData[Total loans],tblData[State],$A64,tblData[Year],B$56) -> 22515 | C64: =SUMIFS(tblData[Total loans],tblData[State],$A64,tblData[Year],C$56) -> 28264 | D64: =SUMIFS(tblData[Total loans],tblData[State],$A64,tblData[Year],D$56) -> 48122 | E64: =SUMIFS(tblData[Total loans],tblData[State],$A64,tblData[Year],E$56) -> 53490 | F64: =SUMIFS(tblData[Total loans],tblData[State],$A64,tblData[Year],F$56) -> 26511 | G64: =SUMIFS(tblData[Total loans],tblData[State],$A64,tblData[Year],G$56) -> 17361 | H64: =SUMIFS(tblData[Total loans],tblData[State],$A64,tblData[Year],H$56) -> 19413 | I64: =SUMIFS(tblData[Total loans],tblData[State],$A64,tblData[Year],I$56) -> 21984
A65: District of Columbia | B65: =SUMIFS(tblData[Total loans],tblData[State],$A65,tblData[Year],B$56) -> 13446 | C65: =SUMIFS(tblData[Total loans],tblData[State],$A65,tblData[Year],C$56) -> 17529 | D65: =SUMIFS(tblData[Total loans],tblData[State],$A65,tblData[Year],D$56) -> 31070 | E65: =SUMIFS(tblData[Total loans],tblData[State],$A65,tblData[Year],E$56) -> 30212 | F65: =SUMIFS(tblData[Total loans],tblData[State],$A65,tblData[Year],F$56) -> 12373 | G65: =SUMIFS(tblData[Total loans],tblData[State],$A65,tblData[Year],G$56) -> 7348 | H65: =SUMIFS(tblData[Total loans],tblData[State],$A65,tblData[Year],H$56) -> 7280 | I65: =SUMIFS(tblData[Total loans],tblData[State],$A65,tblData[Year],I$56) -> 8048
A66: Florida | B66: =SUMIFS(tblData[Total loans],tblData[State],$A66,tblData[Year],B$56) -> 472199 | C66: =SUMIFS(tblData[Total loans],tblData[State],$A66,tblData[Year],C$56) -> 560119 | D66: =SUMIFS(tblData[Total loans],tblData[State],$A66,tblData[Year],D$56) -> 856194 | E66: =SUMIFS(tblData[Total loans],tblData[State],$A66,tblData[Year],E$56) -> 970009 | F66: =SUMIFS(tblData[Total loans],tblData[State],$A66,tblData[Year],F$56) -> 557944 | G66: =SUMIFS(tblData[Total loans],tblData[State],$A66,tblData[Year],G$56) -> 384863 | H66: =SUMIFS(tblData[Total loans],tblData[State],$A66,tblData[Year],H$56) -> 397859 | I66: =SUMIFS(tblData[Total loans],tblData[State],$A66,tblData[Year],I$56) -> 411753
A67: Georgia | B67: =SUMIFS(tblData[Total loans],tblData[State],$A67,tblData[Year],B$56) -> 227602 | C67: =SUMIFS(tblData[Total loans],tblData[State],$A67,tblData[Year],C$56) -> 273520 | D67: =SUMIFS(tblData[Total loans],tblData[State],$A67,tblData[Year],D$56) -> 431238 | E67: =SUMIFS(tblData[Total loans],tblData[State],$A67,tblData[Year],E$56) -> 460507 | F67: =SUMIFS(tblData[Total loans],tblData[State],$A67,tblData[Year],F$56) -> 253891 | G67: =SUMIFS(tblData[Total loans],tblData[State],$A67,tblData[Year],G$56) -> 172815 | H67: =SUMIFS(tblData[Total loans],tblData[State],$A67,tblData[Year],H$56) -> 189618 | I67: =SUMIFS(tblData[Total loans],tblData[State],$A67,tblData[Year],I$56) -> 204590
A68: Hawaii | B68: =SUMIFS(tblData[Total loans],tblData[State],$A68,tblData[Year],B$56) -> 24296 | C68: =SUMIFS(tblData[Total loans],tblData[State],$A68,tblData[Year],C$56) -> 31136 | D68: =SUMIFS(tblData[Total loans],tblData[State],$A68,tblData[Year],D$56) -> 54317 | E68: =SUMIFS(tblData[Total loans],tblData[State],$A68,tblData[Year],E$56) -> 56609 | F68: =SUMIFS(tblData[Total loans],tblData[State],$A68,tblData[Year],F$56) -> 24688 | G68: =SUMIFS(tblData[Total loans],tblData[State],$A68,tblData[Year],G$56) -> 12213 | H68: =SUMIFS(tblData[Total loans],tblData[State],$A68,tblData[Year],H$56) -> 13131 | I68: =SUMIFS(tblData[Total loans],tblData[State],$A68,tblData[Year],I$56) -> 16110
... A107: Wyoming | B107: =SUMIFS(tblData[Total loans],tblData[State],$A107,tblData[Year],B$56) -> 12706 | C107: =SUMIFS(tblData[Total loans],tblData[State],$A107,tblData[Year],C$56) -> 14987 | D107: =SUMIFS(tblData[Total loans],tblData[State],$A107,tblData[Year],D$56) -> 25244 | E107: =SUMIFS(tblData[Total loans],tblData[State],$A107,tblData[Year],E$56) -> 25569 | F107: =SUMIFS(tblData[Total loans],tblData[State],$A107,tblData[Year],F$56) -> 12898 | G107: =SUMIFS(tblData[Total loans],tblData[State],$A107,tblData[Year],G$56) -> 8152 | H107: =SUMIFS(tblData[Total loans],tblData[State],$A107,tblData[Year],H$56) -> 9423 | I107: =SUMIFS(tblData[Total loans],tblData[State],$A107,tblData[Year],I$56) -> 11286
